Workbook

Sheet Statement
A1: Bank Statement
A2: Paste the bank statement here. Matching is automatic.
A4: Date | B4: Description | C4: Reference | D4: Amount | E4: Matched? | F4: Matched to
E5: =IF(D5="","",IF(COUNTIFS(Ledger!$D$5:$D$154,D5)>0,"Yes","No")) | F5: =IF(E5="","",IF(E5="No","",IFERROR(INDEX(Ledger!$C$5:$C$154,MATCH(D5,Ledger!$D$5:$D$154,0)),"")))
E6: =IF(D6="","",IF(COUNTIFS(Ledger!$D$5:$D$154,D6)>0,"Yes","No")) | F6: =IF(E6="","",IF(E6="No","",IFERROR(INDEX(Ledger!$C$5:$C$154,MATCH(D6,Ledger!$D$5:$D$154,0)),"")))
E7: =IF(D7="","",IF(COUNTIFS(Ledger!$D$5:$D$154,D7)>0,"Yes","No")) | F7: =IF(E7="","",IF(E7="No","",IFERROR(INDEX(Ledger!$C$5:$C$154,MATCH(D7,Ledger!$D$5:$D$154,0)),"")))
E8: =IF(D8="","",IF(COUNTIFS(Ledger!$D$5:$D$154,D8)>0,"Yes","No")) | F8: =IF(E8="","",IF(E8="No","",IFERROR(INDEX(Ledger!$C$5:$C$154,MATCH(D8,Ledger!$D$5:$D$154,0)),"")))
E9: =IF(D9="","",IF(COUNTIFS(Ledger!$D$5:$D$154,D9)>0,"Yes","No")) | F9: =IF(E9="","",IF(E9="No","",IFERROR(INDEX(Ledger!$C$5:$C$154,MATCH(D9,Ledger!$D$5:$D$154,0)),"")))
E10: =IF(D10="","",IF(COUNTIFS(Ledger!$D$5:$D$154,D10)>0,"Yes","No")) | F10: =IF(E10="","",IF(E10="No","",IFERROR(INDEX(Ledger!$C$5:$C$154,MATCH(D10,Ledger!$D$5:$D$154,0)),"")))
E11: =IF(D11="","",IF(COUNTIFS(Ledger!$D$5:$D$154,D11)>0,"Yes","No")) | F11: =IF(E11="","",IF(E11="No","",IFERROR(INDEX(Ledger!$C$5:$C$154,MATCH(D11,Ledger!$D$5:$D$154,0)),"")))
E12: =IF(D12="","",IF(COUNTIFS(Ledger!$D$5:$D$154,D12)>0,"Yes","No")) | F12: =IF(E12="","",IF(E12="No","",IFERROR(INDEX(Ledger!$C$5:$C$154,MATCH(D12,Ledger!$D$5:$D$154,0)),"")))
E13: =IF(D13="","",IF(COUNTIFS(Ledger!$D$5:$D$154,D13)>0,"Yes","No")) | F13: =IF(E13="","",IF(E13="No","",IFERROR(INDEX(Ledger!$C$5:$C$154,MATCH(D13,Ledger!$D$5:$D$154,0)),"")))
E14: =IF(D14="","",IF(COUNTIFS(Ledger!$D$5:$D$154,D14)>0,"Yes","No")) | F14: =IF(E14="","",IF(E14="No","",IFERROR(INDEX(Ledger!$C$5:$C$154,MATCH(D14,Ledger!$D$5:$D$154,0)),"")))
E15: =IF(D15="","",IF(COUNTIFS(Ledger!$D$5:$D$154,D15)>0,"Yes","No")) | F15: =IF(E15="","",IF(E15="No","",IFERROR(INDEX(Ledger!$C$5:$C$154,MATCH(D15,Ledger!$D$5:$D$154,0)),"")))
E16: =IF(D16="","",IF(COUNTIFS(Ledger!$D$5:$D$154,D16)>0,"Yes","No")) | F16: =IF(E16="","",IF(E16="No","",IFERROR(INDEX(Ledger!$C$5:$C$154,MATCH(D16,Ledger!$D$5:$D$154,0)),"")))
... E154: =IF(D154="","",IF(COUNTIFS(Ledger!$D$5:$D$154,D154)>0,"Yes","No")) | F154: =IF(E154="","",IF(E154="No","",IFERROR(INDEX(Ledger!$C$5:$C$154,MATCH(D154,Ledger!$D$5:$D$154,0)),"")))

Sheet Ledger
A1: Cash Book / Ledger
A2: Your own record of the same period.
A4: Date | B4: Description | C4: Reference | D4: Amount | E4: Matched? | F4: Matched to
E5: =IF(D5="","",IF(COUNTIFS(Statement!$D$5:$D$154,D5)>0,"Yes","No")) | F5: =IF(E5="","",IF(E5="No","",IFERROR(INDEX(Statement!$C$5:$C$154,MATCH(D5,Statement!$D$5:$D$154,0)),"")))
E6: =IF(D6="","",IF(COUNTIFS(Statement!$D$5:$D$154,D6)>0,"Yes","No")) | F6: =IF(E6="","",IF(E6="No","",IFERROR(INDEX(Statement!$C$5:$C$154,MATCH(D6,Statement!$D$5:$D$154,0)),"")))
E7: =IF(D7="","",IF(COUNTIFS(Statement!$D$5:$D$154,D7)>0,"Yes","No")) | F7: =IF(E7="","",IF(E7="No","",IFERROR(INDEX(Statement!$C$5:$C$154,MATCH(D7,Statement!$D$5:$D$154,0)),"")))
E8: =IF(D8="","",IF(COUNTIFS(Statement!$D$5:$D$154,D8)>0,"Yes","No")) | F8: =IF(E8="","",IF(E8="No","",IFERROR(INDEX(Statement!$C$5:$C$154,MATCH(D8,Statement!$D$5:$D$154,0)),"")))
E9: =IF(D9="","",IF(COUNTIFS(Statement!$D$5:$D$154,D9)>0,"Yes","No")) | F9: =IF(E9="","",IF(E9="No","",IFERROR(INDEX(Statement!$C$5:$C$154,MATCH(D9,Statement!$D$5:$D$154,0)),"")))
E10: =IF(D10="","",IF(COUNTIFS(Statement!$D$5:$D$154,D10)>0,"Yes","No")) | F10: =IF(E10="","",IF(E10="No","",IFERROR(INDEX(Statement!$C$5:$C$154,MATCH(D10,Statement!$D$5:$D$154,0)),"")))
E11: =IF(D11="","",IF(COUNTIFS(Statement!$D$5:$D$154,D11)>0,"Yes","No")) | F11: =IF(E11="","",IF(E11="No","",IFERROR(INDEX(Statement!$C$5:$C$154,MATCH(D11,Statement!$D$5:$D$154,0)),"")))
E12: =IF(D12="","",IF(COUNTIFS(Statement!$D$5:$D$154,D12)>0,"Yes","No")) | F12: =IF(E12="","",IF(E12="No","",IFERROR(INDEX(Statement!$C$5:$C$154,MATCH(D12,Statement!$D$5:$D$154,0)),"")))
E13: =IF(D13="","",IF(COUNTIFS(Statement!$D$5:$D$154,D13)>0,"Yes","No")) | F13: =IF(E13="","",IF(E13="No","",IFERROR(INDEX(Statement!$C$5:$C$154,MATCH(D13,Statement!$D$5:$D$154,0)),"")))
E14: =IF(D14="","",IF(COUNTIFS(Statement!$D$5:$D$154,D14)>0,"Yes","No")) | F14: =IF(E14="","",IF(E14="No","",IFERROR(INDEX(Statement!$C$5:$C$154,MATCH(D14,Statement!$D$5:$D$154,0)),"")))
E15: =IF(D15="","",IF(COUNTIFS(Statement!$D$5:$D$154,D15)>0,"Yes","No")) | F15: =IF(E15="","",IF(E15="No","",IFERROR(INDEX(Statement!$C$5:$C$154,MATCH(D15,Statement!$D$5:$D$154,0)),"")))
E16: =IF(D16="","",IF(COUNTIFS(Statement!$D$5:$D$154,D16)>0,"Yes","No")) | F16: =IF(E16="","",IF(E16="No","",IFERROR(INDEX(Statement!$C$5:$C$154,MATCH(D16,Statement!$D$5:$D$154,0)),"")))
... E154: =IF(D154="","",IF(COUNTIFS(Statement!$D$5:$D$154,D154)>0,"Yes","No")) | F154: =IF(E154="","",IF(E154="No","",IFERROR(INDEX(Statement!$C$5:$C$154,MATCH(D154,Statement!$D$5:$D$154,0)),"")))

Sheet Reconciliation
A1: Reconciliation Statement
A2: The formal reconciliation. All figures calculate.
A5: Balance per bank statement | C5: =SUM(Statement!D5:D154) -> 0 | D5: Sum of every statement line.
A7: Add: outstanding lodgements | C7: =SUMIFS(Ledger!$D$5:$D$154,Ledger!$E$5:$E$154,"No",Ledger!$D$5:$D$154,">0") -> 0 | D7: Receipts in your books, not yet on the statement.
A8: Less: unpresented cheques | C8: =SUMIFS(Ledger!$D$5:$D$154,Ledger!$E$5:$E$154,"No",Ledger!$D$5:$D$154,"<0") -> 0 | D8: Payments made but not yet cleared. Shown negative.
A9: Less: items on the statement only | C9: =-SUMIFS(Statement!$D$5:$D$154,Statement!$E$5:$E$154,"No") -> 0 | D9: Bank charges and interest you have not yet posted.
A11: Adjusted bank balance | C11: =C5+C7+C8+C9 -> 0 | D11: What the statement would say once everything clears.
A13: Balance per cash book | C13: =SUM(Ledger!D5:D154) -> 0 | D13: Sum of every ledger line.
A15: Difference | C15: =C11-C13 -> 0 | D15: Must be zero. If it is not, something is unmatched or entered twice.
A17: Unmatched items
B18: Count | C18: Value
A19: Statement lines unmatched | B19: =COUNTIFS(Statement!$E$5:$E$154,"No") -> 0 | C19: =SUMIFS(Statement!$D$5:$D$154,Statement!$E$5:$E$154,"No") -> 0
A20: Ledger lines unmatched | B20: =COUNTIFS(Ledger!$E$5:$E$154,"No") -> 0 | C20: =SUMIFS(Ledger!$D$5:$D$154,Ledger!$E$5:$E$154,"No") -> 0

Sheet Read me
A1: How this workbook works
A2: Explore Excel · exploreexcel.com
A4: What this is
A5: A bank reconciliation that matches statement lines to ledger lines automatically and produces the formal reconciliation statement.
A7: How the matching works
A8: Each line looks for its exact amount on the other sheet. If it finds one, the line is marked Yes and the matching description is pulled across. If not, it is marked No and turns red.
A10: The honest limitation
A11: Matching is on amount alone. Two different transactions for the same amount will match each other. That is a real weakness and you should know about it rather than discover it. Use the reference column and your own eyes on anything that looks suspicious — automation narrows the search, it does not replace the judgement.
A13: Reading the reconciliation
A14: The Difference cell must be zero. If it is not, work through the unmatched items at the bottom. In practice the cause is almost always a timing difference, a transposition, or something posted twice.
A16: Sign convention
A17: Money in is positive, money out is negative, on both sheets. Outstanding lodgements pick up unmatched positives; unpresented cheques pick up unmatched negatives. If you enter payments as positive numbers the reconciliation will not work.
