Workbook

Sheet Budget
A1: Annual Budget
A2: Explore Excel · exploreexcel.com · Enter the approved budget by month
A4: Cost line | B4: Category | C4: Department | D4: Jan | E4: Feb | F4: Mar | G4: Apr | H4: May | I4: Jun | J4: Jul | K4: Aug | L4: Sep | M4: Oct | N4: Nov | O4: Dec | P4: Full year
A5: Salaries and wages | B5: Staff | C5: Sales | D5: 0 | E5: 0 | F5: 0 | G5: 0 | H5: 0 | I5: 0 | J5: 0 | K5: 0 | L5: 0 | M5: 0 | N5: 0 | O5: 0 | P5: =SUM(D5:O5) -> 0
A6: Employee benefits | B6: Staff | C6: Sales | D6: 0 | E6: 0 | F6: 0 | G6: 0 | H6: 0 | I6: 0 | J6: 0 | K6: 0 | L6: 0 | M6: 0 | N6: 0 | O6: 0 | P6: =SUM(D6:O6) -> 0
A7: Training | B7: Staff | C7: Sales | D7: 0 | E7: 0 | F7: 0 | G7: 0 | H7: 0 | I7: 0 | J7: 0 | K7: 0 | L7: 0 | M7: 0 | N7: 0 | O7: 0 | P7: =SUM(D7:O7) -> 0
A8: Rent | B8: Premises | C8: Sales | D8: 0 | E8: 0 | F8: 0 | G8: 0 | H8: 0 | I8: 0 | J8: 0 | K8: 0 | L8: 0 | M8: 0 | N8: 0 | O8: 0 | P8: =SUM(D8:O8) -> 0
A9: Utilities | B9: Premises | C9: Sales | D9: 0 | E9: 0 | F9: 0 | G9: 0 | H9: 0 | I9: 0 | J9: 0 | K9: 0 | L9: 0 | M9: 0 | N9: 0 | O9: 0 | P9: =SUM(D9:O9) -> 0
A10: Repairs and maintenance | B10: Premises | C10: Sales | D10: 0 | E10: 0 | F10: 0 | G10: 0 | H10: 0 | I10: 0 | J10: 0 | K10: 0 | L10: 0 | M10: 0 | N10: 0 | O10: 0 | P10: =SUM(D10:O10) -> 0
A11: Software licences | B11: Technology | C11: Sales | D11: 0 | E11: 0 | F11: 0 | G11: 0 | H11: 0 | I11: 0 | J11: 0 | K11: 0 | L11: 0 | M11: 0 | N11: 0 | O11: 0 | P11: =SUM(D11:O11) -> 0
A12: Hardware | B12: Technology | C12: Sales | D12: 0 | E12: 0 | F12: 0 | G12: 0 | H12: 0 | I12: 0 | J12: 0 | K12: 0 | L12: 0 | M12: 0 | N12: 0 | O12: 0 | P12: =SUM(D12:O12) -> 0
A13: Advertising | B13: Marketing | C13: Sales | D13: 0 | E13: 0 | F13: 0 | G13: 0 | H13: 0 | I13: 0 | J13: 0 | K13: 0 | L13: 0 | M13: 0 | N13: 0 | O13: 0 | P13: =SUM(D13:O13) -> 0
A14: Travel and entertainment | B14: Other | C14: Sales | D14: 0 | E14: 0 | F14: 0 | G14: 0 | H14: 0 | I14: 0 | J14: 0 | K14: 0 | L14: 0 | M14: 0 | N14: 0 | O14: 0 | P14: =SUM(D14:O14) -> 0
A15: Professional fees | B15: Other | C15: Sales | D15: 0 | E15: 0 | F15: 0 | G15: 0 | H15: 0 | I15: 0 | J15: 0 | K15: 0 | L15: 0 | M15: 0 | N15: 0 | O15: 0 | P15: =SUM(D15:O15) -> 0
A16: Office supplies | B16: Other | C16: Sales | D16: 0 | E16: 0 | F16: 0 | G16: 0 | H16: 0 | I16: 0 | J16: 0 | K16: 0 | L16: 0 | M16: 0 | N16: 0 | O16: 0 | P16: =SUM(D16:O16) -> 0
... A76: Office supplies | B76: Other | C76: IT | D76: 0 | E76: 0 | F76: 0 | G76: 0 | H76: 0 | I76: 0 | J76: 0 | K76: 0 | L76: 0 | M76: 0 | N76: 0 | O76: 0 | P76: =SUM(D76:O76) -> 0
A77: TOTAL BUDGET | D77: =SUM(D5:D76) -> 0 | E77: =SUM(E5:E76) -> 0 | F77: =SUM(F5:F76) -> 0 | G77: =SUM(G5:G76) -> 0 | H77: =SUM(H5:H76) -> 0 | I77: =SUM(I5:I76) -> 0 | J77: =SUM(J5:J76) -> 0 | K77: =SUM(K5:K76) -> 0 | ... P77: =SUM(P5:P76) -> 0

Sheet Actual
A1: Actual Spend
A2: Same layout as Budget. Enter what was actually spent.
A4: Cost line | B4: Category | C4: Department | D4: Jan | E4: Feb | F4: Mar | G4: Apr | H4: May | I4: Jun | J4: Jul | K4: Aug | L4: Sep | M4: Oct | N4: Nov | O4: Dec | P4: Full year
A5: Salaries and wages | B5: Staff | C5: Sales | D5: 0 | E5: 0 | F5: 0 | G5: 0 | H5: 0 | I5: 0 | J5: 0 | K5: 0 | L5: 0 | M5: 0 | N5: 0 | O5: 0 | P5: =SUM(D5:O5) -> 0
A6: Employee benefits | B6: Staff | C6: Sales | D6: 0 | E6: 0 | F6: 0 | G6: 0 | H6: 0 | I6: 0 | J6: 0 | K6: 0 | L6: 0 | M6: 0 | N6: 0 | O6: 0 | P6: =SUM(D6:O6) -> 0
A7: Training | B7: Staff | C7: Sales | D7: 0 | E7: 0 | F7: 0 | G7: 0 | H7: 0 | I7: 0 | J7: 0 | K7: 0 | L7: 0 | M7: 0 | N7: 0 | O7: 0 | P7: =SUM(D7:O7) -> 0
A8: Rent | B8: Premises | C8: Sales | D8: 0 | E8: 0 | F8: 0 | G8: 0 | H8: 0 | I8: 0 | J8: 0 | K8: 0 | L8: 0 | M8: 0 | N8: 0 | O8: 0 | P8: =SUM(D8:O8) -> 0
A9: Utilities | B9: Premises | C9: Sales | D9: 0 | E9: 0 | F9: 0 | G9: 0 | H9: 0 | I9: 0 | J9: 0 | K9: 0 | L9: 0 | M9: 0 | N9: 0 | O9: 0 | P9: =SUM(D9:O9) -> 0
A10: Repairs and maintenance | B10: Premises | C10: Sales | D10: 0 | E10: 0 | F10: 0 | G10: 0 | H10: 0 | I10: 0 | J10: 0 | K10: 0 | L10: 0 | M10: 0 | N10: 0 | O10: 0 | P10: =SUM(D10:O10) -> 0
A11: Software licences | B11: Technology | C11: Sales | D11: 0 | E11: 0 | F11: 0 | G11: 0 | H11: 0 | I11: 0 | J11: 0 | K11: 0 | L11: 0 | M11: 0 | N11: 0 | O11: 0 | P11: =SUM(D11:O11) -> 0
A12: Hardware | B12: Technology | C12: Sales | D12: 0 | E12: 0 | F12: 0 | G12: 0 | H12: 0 | I12: 0 | J12: 0 | K12: 0 | L12: 0 | M12: 0 | N12: 0 | O12: 0 | P12: =SUM(D12:O12) -> 0
A13: Advertising | B13: Marketing | C13: Sales | D13: 0 | E13: 0 | F13: 0 | G13: 0 | H13: 0 | I13: 0 | J13: 0 | K13: 0 | L13: 0 | M13: 0 | N13: 0 | O13: 0 | P13: =SUM(D13:O13) -> 0
A14: Travel and entertainment | B14: Other | C14: Sales | D14: 0 | E14: 0 | F14: 0 | G14: 0 | H14: 0 | I14: 0 | J14: 0 | K14: 0 | L14: 0 | M14: 0 | N14: 0 | O14: 0 | P14: =SUM(D14:O14) -> 0
A15: Professional fees | B15: Other | C15: Sales | D15: 0 | E15: 0 | F15: 0 | G15: 0 | H15: 0 | I15: 0 | J15: 0 | K15: 0 | L15: 0 | M15: 0 | N15: 0 | O15: 0 | P15: =SUM(D15:O15) -> 0
A16: Office supplies | B16: Other | C16: Sales | D16: 0 | E16: 0 | F16: 0 | G16: 0 | H16: 0 | I16: 0 | J16: 0 | K16: 0 | L16: 0 | M16: 0 | N16: 0 | O16: 0 | P16: =SUM(D16:O16) -> 0
... A76: Office supplies | B76: Other | C76: IT | D76: 0 | E76: 0 | F76: 0 | G76: 0 | H76: 0 | I76: 0 | J76: 0 | K76: 0 | L76: 0 | M76: 0 | N76: 0 | O76: 0 | P76: =SUM(D76:O76) -> 0
A77: TOTAL ACTUAL | D77: =SUM(D5:D76) -> 0 | E77: =SUM(E5:E76) -> 0 | F77: =SUM(F5:F76) -> 0 | G77: =SUM(G5:G76) -> 0 | H77: =SUM(H5:H76) -> 0 | I77: =SUM(I5:I76) -> 0 | J77: =SUM(J5:J76) -> 0 | K77: =SUM(K5:K76) -> 0 | ... P77: =SUM(P5:P76) -> 0

Sheet Variance
A1: Variance Analysis
A2: Actual less budget. Positive means overspent.
A4: Cost line | B4: Category | C4: Department | D4: Jan | E4: Feb | F4: Mar | G4: Apr | H4: May | I4: Jun | J4: Jul | K4: Aug | L4: Sep | M4: Oct | N4: Nov | O4: Dec | P4: Full year
A5: =Budget!A5 -> Salaries and wages | B5: =Budget!B5 -> Staff | C5: =Budget!C5 -> Sales | D5: =Actual!D5-Budget!D5 -> 0 | E5: =Actual!E5-Budget!E5 -> 0 | F5: =Actual!F5-Budget!F5 -> 0 | G5: =Actual!G5-Budget!G5 -> 0 | H5: =Actual!H5-Budget!H5 -> 0 | I5: =Actual!I5-Budget!I5 -> 0 | J5: =Actual!J5-Budget!J5 -> 0 | K5: =Actual!K5-Budget!K5 -> 0 | ... P5: =Actual!P5-Budget!P5 -> 0
A6: =Budget!A6 -> Employee benefits | B6: =Budget!B6 -> Staff | C6: =Budget!C6 -> Sales | D6: =Actual!D6-Budget!D6 -> 0 | E6: =Actual!E6-Budget!E6 -> 0 | F6: =Actual!F6-Budget!F6 -> 0 | G6: =Actual!G6-Budget!G6 -> 0 | H6: =Actual!H6-Budget!H6 -> 0 | I6: =Actual!I6-Budget!I6 -> 0 | J6: =Actual!J6-Budget!J6 -> 0 | K6: =Actual!K6-Budget!K6 -> 0 | ... P6: =Actual!P6-Budget!P6 -> 0
A7: =Budget!A7 -> Training | B7: =Budget!B7 -> Staff | C7: =Budget!C7 -> Sales | D7: =Actual!D7-Budget!D7 -> 0 | E7: =Actual!E7-Budget!E7 -> 0 | F7: =Actual!F7-Budget!F7 -> 0 | G7: =Actual!G7-Budget!G7 -> 0 | H7: =Actual!H7-Budget!H7 -> 0 | I7: =Actual!I7-Budget!I7 -> 0 | J7: =Actual!J7-Budget!J7 -> 0 | K7: =Actual!K7-Budget!K7 -> 0 | ... P7: =Actual!P7-Budget!P7 -> 0
A8: =Budget!A8 -> Rent | B8: =Budget!B8 -> Premises | C8: =Budget!C8 -> Sales | D8: =Actual!D8-Budget!D8 -> 0 | E8: =Actual!E8-Budget!E8 -> 0 | F8: =Actual!F8-Budget!F8 -> 0 | G8: =Actual!G8-Budget!G8 -> 0 | H8: =Actual!H8-Budget!H8 -> 0 | I8: =Actual!I8-Budget!I8 -> 0 | J8: =Actual!J8-Budget!J8 -> 0 | K8: =Actual!K8-Budget!K8 -> 0 | ... P8: =Actual!P8-Budget!P8 -> 0
A9: =Budget!A9 -> Utilities | B9: =Budget!B9 -> Premises | C9: =Budget!C9 -> Sales | D9: =Actual!D9-Budget!D9 -> 0 | E9: =Actual!E9-Budget!E9 -> 0 | F9: =Actual!F9-Budget!F9 -> 0 | G9: =Actual!G9-Budget!G9 -> 0 | H9: =Actual!H9-Budget!H9 -> 0 | I9: =Actual!I9-Budget!I9 -> 0 | J9: =Actual!J9-Budget!J9 -> 0 | K9: =Actual!K9-Budget!K9 -> 0 | ... P9: =Actual!P9-Budget!P9 -> 0
A10: =Budget!A10 -> Repairs and maintenance | B10: =Budget!B10 -> Premises | C10: =Budget!C10 -> Sales | D10: =Actual!D10-Budget!D10 -> 0 | E10: =Actual!E10-Budget!E10 -> 0 | F10: =Actual!F10-Budget!F10 -> 0 | G10: =Actual!G10-Budget!G10 -> 0 | H10: =Actual!H10-Budget!H10 -> 0 | I10: =Actual!I10-Budget!I10 -> 0 | J10: =Actual!J10-Budget!J10 -> 0 | K10: =Actual!K10-Budget!K10 -> 0 | ... P10: =Actual!P10-Budget!P10 -> 0
A11: =Budget!A11 -> Software licences | B11: =Budget!B11 -> Technology | C11: =Budget!C11 -> Sales | D11: =Actual!D11-Budget!D11 -> 0 | E11: =Actual!E11-Budget!E11 -> 0 | F11: =Actual!F11-Budget!F11 -> 0 | G11: =Actual!G11-Budget!G11 -> 0 | H11: =Actual!H11-Budget!H11 -> 0 | I11: =Actual!I11-Budget!I11 -> 0 | J11: =Actual!J11-Budget!J11 -> 0 | K11: =Actual!K11-Budget!K11 -> 0 | ... P11: =Actual!P11-Budget!P11 -> 0
A12: =Budget!A12 -> Hardware | B12: =Budget!B12 -> Technology | C12: =Budget!C12 -> Sales | D12: =Actual!D12-Budget!D12 -> 0 | E12: =Actual!E12-Budget!E12 -> 0 | F12: =Actual!F12-Budget!F12 -> 0 | G12: =Actual!G12-Budget!G12 -> 0 | H12: =Actual!H12-Budget!H12 -> 0 | I12: =Actual!I12-Budget!I12 -> 0 | J12: =Actual!J12-Budget!J12 -> 0 | K12: =Actual!K12-Budget!K12 -> 0 | ... P12: =Actual!P12-Budget!P12 -> 0
A13: =Budget!A13 -> Advertising | B13: =Budget!B13 -> Marketing | C13: =Budget!C13 -> Sales | D13: =Actual!D13-Budget!D13 -> 0 | E13: =Actual!E13-Budget!E13 -> 0 | F13: =Actual!F13-Budget!F13 -> 0 | G13: =Actual!G13-Budget!G13 -> 0 | H13: =Actual!H13-Budget!H13 -> 0 | I13: =Actual!I13-Budget!I13 -> 0 | J13: =Actual!J13-Budget!J13 -> 0 | K13: =Actual!K13-Budget!K13 -> 0 | ... P13: =Actual!P13-Budget!P13 -> 0
A14: =Budget!A14 -> Travel and entertainment | B14: =Budget!B14 -> Other | C14: =Budget!C14 -> Sales | D14: =Actual!D14-Budget!D14 -> 0 | E14: =Actual!E14-Budget!E14 -> 0 | F14: =Actual!F14-Budget!F14 -> 0 | G14: =Actual!G14-Budget!G14 -> 0 | H14: =Actual!H14-Budget!H14 -> 0 | I14: =Actual!I14-Budget!I14 -> 0 | J14: =Actual!J14-Budget!J14 -> 0 | K14: =Actual!K14-Budget!K14 -> 0 | ... P14: =Actual!P14-Budget!P14 -> 0
A15: =Budget!A15 -> Professional fees | B15: =Budget!B15 -> Other | C15: =Budget!C15 -> Sales | D15: =Actual!D15-Budget!D15 -> 0 | E15: =Actual!E15-Budget!E15 -> 0 | F15: =Actual!F15-Budget!F15 -> 0 | G15: =Actual!G15-Budget!G15 -> 0 | H15: =Actual!H15-Budget!H15 -> 0 | I15: =Actual!I15-Budget!I15 -> 0 | J15: =Actual!J15-Budget!J15 -> 0 | K15: =Actual!K15-Budget!K15 -> 0 | ... P15: =Actual!P15-Budget!P15 -> 0
A16: =Budget!A16 -> Office supplies | B16: =Budget!B16 -> Other | C16: =Budget!C16 -> Sales | D16: =Actual!D16-Budget!D16 -> 0 | E16: =Actual!E16-Budget!E16 -> 0 | F16: =Actual!F16-Budget!F16 -> 0 | G16: =Actual!G16-Budget!G16 -> 0 | H16: =Actual!H16-Budget!H16 -> 0 | I16: =Actual!I16-Budget!I16 -> 0 | J16: =Actual!J16-Budget!J16 -> 0 | K16: =Actual!K16-Budget!K16 -> 0 | ... P16: =Actual!P16-Budget!P16 -> 0
... A76: =Budget!A76 -> Office supplies | B76: =Budget!B76 -> Other | C76: =Budget!C76 -> IT | D76: =Actual!D76-Budget!D76 -> 0 | E76: =Actual!E76-Budget!E76 -> 0 | F76: =Actual!F76-Budget!F76 -> 0 | G76: =Actual!G76-Budget!G76 -> 0 | H76: =Actual!H76-Budget!H76 -> 0 | I76: =Actual!I76-Budget!I76 -> 0 | J76: =Actual!J76-Budget!J76 -> 0 | K76: =Actual!K76-Budget!K76 -> 0 | ... P76: =Actual!P76-Budget!P76 -> 0
A77: TOTAL VARIANCE | D77: =SUM(D5:D76) -> 0 | E77: =SUM(E5:E76) -> 0 | F77: =SUM(F5:F76) -> 0 | G77: =SUM(G5:G76) -> 0 | H77: =SUM(H5:H76) -> 0 | I77: =SUM(I5:I76) -> 0 | J77: =SUM(J5:J76) -> 0 | K77: =SUM(K5:K76) -> 0 | ... P77: =SUM(P5:P76) -> 0

Sheet Dashboard
A1: Budget Dashboard
A2: Everything here reads from the other three sheets.
A4: Months elapsed | C4: 4 | D4: Set this to the number of months of actual data entered. Drives the YTD columns.
A6: By department
A7: Department | B7: Budget YTD | C7: Actual YTD | D7: Variance | E7: Variance % | F7: Status
A8: Sales | B8: =SUMPRODUCT((Budget!$C$5:$C$76=A8)*Budget!$D$5:$O$76*(COLUMN(Budget!$D$5:$O$5)-COLUMN(Budget!$D$5)<$C$4)) -> 0 | C8: =SUMPRODUCT((Actual!$C$5:$C$76=A8)*Actual!$D$5:$O$76*(COLUMN(Actual!$D$5:$O$5)-COLUMN(Actual!$D$5)<$C$4)) -> 0 | D8: =C8-B8 -> 0 | E8: =IF(B8=0,0,D8/B8) -> 0 | F8: =IF(B8=0,"No budget",IF(E8>0.1,"Over",IF(E8<-0.1,"Under","On track"))) -> No budget
A9: Marketing | B9: =SUMPRODUCT((Budget!$C$5:$C$76=A9)*Budget!$D$5:$O$76*(COLUMN(Budget!$D$5:$O$5)-COLUMN(Budget!$D$5)<$C$4)) -> 0 | C9: =SUMPRODUCT((Actual!$C$5:$C$76=A9)*Actual!$D$5:$O$76*(COLUMN(Actual!$D$5:$O$5)-COLUMN(Actual!$D$5)<$C$4)) -> 0 | D9: =C9-B9 -> 0 | E9: =IF(B9=0,0,D9/B9) -> 0 | F9: =IF(B9=0,"No budget",IF(E9>0.1,"Over",IF(E9<-0.1,"Under","On track"))) -> No budget
A10: Operations | B10: =SUMPRODUCT((Budget!$C$5:$C$76=A10)*Budget!$D$5:$O$76*(COLUMN(Budget!$D$5:$O$5)-COLUMN(Budget!$D$5)<$C$4)) -> 0 | C10: =SUMPRODUCT((Actual!$C$5:$C$76=A10)*Actual!$D$5:$O$76*(COLUMN(Actual!$D$5:$O$5)-COLUMN(Actual!$D$5)<$C$4)) -> 0 | D10: =C10-B10 -> 0 | E10: =IF(B10=0,0,D10/B10) -> 0 | F10: =IF(B10=0,"No budget",IF(E10>0.1,"Over",IF(E10<-0.1,"Under","On track"))) -> No budget
A11: Finance | B11: =SUMPRODUCT((Budget!$C$5:$C$76=A11)*Budget!$D$5:$O$76*(COLUMN(Budget!$D$5:$O$5)-COLUMN(Budget!$D$5)<$C$4)) -> 0 | C11: =SUMPRODUCT((Actual!$C$5:$C$76=A11)*Actual!$D$5:$O$76*(COLUMN(Actual!$D$5:$O$5)-COLUMN(Actual!$D$5)<$C$4)) -> 0 | D11: =C11-B11 -> 0 | E11: =IF(B11=0,0,D11/B11) -> 0 | F11: =IF(B11=0,"No budget",IF(E11>0.1,"Over",IF(E11<-0.1,"Under","On track"))) -> No budget
A12: HR | B12: =SUMPRODUCT((Budget!$C$5:$C$76=A12)*Budget!$D$5:$O$76*(COLUMN(Budget!$D$5:$O$5)-COLUMN(Budget!$D$5)<$C$4)) -> 0 | C12: =SUMPRODUCT((Actual!$C$5:$C$76=A12)*Actual!$D$5:$O$76*(COLUMN(Actual!$D$5:$O$5)-COLUMN(Actual!$D$5)<$C$4)) -> 0 | D12: =C12-B12 -> 0 | E12: =IF(B12=0,0,D12/B12) -> 0 | F12: =IF(B12=0,"No budget",IF(E12>0.1,"Over",IF(E12<-0.1,"Under","On track"))) -> No budget
A13: IT | B13: =SUMPRODUCT((Budget!$C$5:$C$76=A13)*Budget!$D$5:$O$76*(COLUMN(Budget!$D$5:$O$5)-COLUMN(Budget!$D$5)<$C$4)) -> 0 | C13: =SUMPRODUCT((Actual!$C$5:$C$76=A13)*Actual!$D$5:$O$76*(COLUMN(Actual!$D$5:$O$5)-COLUMN(Actual!$D$5)<$C$4)) -> 0 | D13: =C13-B13 -> 0 | E13: =IF(B13=0,0,D13/B13) -> 0 | F13: =IF(B13=0,"No budget",IF(E13>0.1,"Over",IF(E13<-0.1,"Under","On track"))) -> No budget
A14: Total | B14: =SUM(B8:B13) -> 0 | C14: =SUM(C8:C13) -> 0 | D14: =SUM(D8:D13) -> 0 | E14: =IF(B14=0,0,D14/B14) -> 0
A16: By category — full year
A17: Category | B17: Budget | C17: Actual | D17: Variance | E17: Variance %
A18: Staff | B18: =SUMIFS(Budget!$O$5:$O$76,Budget!$B$5:$B$76,A18) -> 0 | C18: =SUMIFS(Actual!$O$5:$O$76,Actual!$B$5:$B$76,A18) -> 0 | D18: =C18-B18 -> 0 | E18: =IF(B18=0,0,D18/B18) -> 0
A19: Premises | B19: =SUMIFS(Budget!$O$5:$O$76,Budget!$B$5:$B$76,A19) -> 0 | C19: =SUMIFS(Actual!$O$5:$O$76,Actual!$B$5:$B$76,A19) -> 0 | D19: =C19-B19 -> 0 | E19: =IF(B19=0,0,D19/B19) -> 0
A20: Technology | B20: =SUMIFS(Budget!$O$5:$O$76,Budget!$B$5:$B$76,A20) -> 0 | C20: =SUMIFS(Actual!$O$5:$O$76,Actual!$B$5:$B$76,A20) -> 0 | D20: =C20-B20 -> 0 | E20: =IF(B20=0,0,D20/B20) -> 0
A21: Marketing | B21: =SUMIFS(Budget!$O$5:$O$76,Budget!$B$5:$B$76,A21) -> 0 | C21: =SUMIFS(Actual!$O$5:$O$76,Actual!$B$5:$B$76,A21) -> 0 | D21: =C21-B21 -> 0 | E21: =IF(B21=0,0,D21/B21) -> 0
A22: Other | B22: =SUMIFS(Budget!$O$5:$O$76,Budget!$B$5:$B$76,A22) -> 0 | C22: =SUMIFS(Actual!$O$5:$O$76,Actual!$B$5:$B$76,A22) -> 0 | D22: =C22-B22 -> 0 | E22: =IF(B22=0,0,D22/B22) -> 0
A23: Total | B23: =SUM(B18:B22) -> 0 | C23: =SUM(C18:C22) -> 0 | D23: =SUM(D18:D22) -> 0 | E23: =IF(B23=0,0,D23/B23) -> 0
A25: Over and Under trigger at ten per cent. Change the 0.1 in column F if your tolerance is tighter.

Sheet Read me
A1: How this workbook works
A2: Explore Excel · exploreexcel.com
A4: What this is
A5: Budget against actual for six departments and twelve cost lines, by month, with variance calculated automatically and a dashboard that summarises both ways.
A7: The three data sheets
A8: Budget and Actual have identical layouts — same rows, same columns. That is deliberate: Variance can then subtract one from the other cell by cell, with no lookups to break.
A10: Filling it in
A11: Enter the approved budget on Budget. As each month closes, enter what was spent on Actual. Variance and Dashboard need no input at all.
A13: The months-elapsed cell
A14: Cell C4 on Dashboard controls how many months the year-to-date figures cover. Set it to 4 after April, and the YTD columns compare four months of budget against four months of actual. Leave it at 12 and you get the full year.
A16: Reading the variance
A17: Positive means you spent more than budget. Red is overspend, green is underspend. This is the expenditure convention — for a revenue budget, the colours would mean the opposite, which is why mixing income and cost in one variance report causes so much confusion.
... A20: Insert the same row on Budget, Actual and Variance so the three stay aligned. If they drift out of step, every variance below the insertion point is wrong — and it will not error, it will just be quietly incorrect.
