Workbook

Sheet Forecast
A1: 13-Week Cash Flow Forecast
A2: Explore Excel · exploreexcel.com · Enter values in blue, everything else calculates
A4: Forecast start date | C4: =Assumptions!B4 -> 2026-01-05
A5: Opening cash balance | C5: =Assumptions!B5 -> 45000
A6: Minimum cash buffer | C6: =Assumptions!B6 -> 20000
A8: Line item | B8: Category | C8: =$C$4+0 -> 46027 | D8: =$C$4+7 -> 46034 | E8: =$C$4+14 -> 46041 | F8: =$C$4+21 -> 46048 | G8: =$C$4+28 -> 46055 | H8: =$C$4+35 -> 46062 | I8: =$C$4+42 -> 46069 | J8: =$C$4+49 -> 46076 | K8: =$C$4+56 -> 46083 | L8: =$C$4+63 -> 46090 | M8: =$C$4+70 -> 46097 | N8: =$C$4+77 -> 46104 | O8: =$C$4+84 -> 46111
A9: RECEIPTS
A10: Cash sales | B10: Trading | C10: 0 | D10: 0 | E10: 0 | F10: 0 | G10: 0 | H10: 0 | I10: 0 | J10: 0 | K10: 0 | L10: 0 | M10: 0 | N10: 0 | O10: 0
A11: Receipts from debtors | B11: Trading | C11: 0 | D11: 0 | E11: 0 | F11: 0 | G11: 0 | H11: 0 | I11: 0 | J11: 0 | K11: 0 | L11: 0 | M11: 0 | N11: 0 | O11: 0
A12: Other income | B12: Trading | C12: 0 | D12: 0 | E12: 0 | F12: 0 | G12: 0 | H12: 0 | I12: 0 | J12: 0 | K12: 0 | L12: 0 | M12: 0 | N12: 0 | O12: 0
A13: Loan drawdown | B13: Financing | C13: 0 | D13: 0 | E13: 0 | F13: 0 | G13: 0 | H13: 0 | I13: 0 | J13: 0 | K13: 0 | L13: 0 | M13: 0 | N13: 0 | O13: 0
A14: Asset disposals | B14: Investing | C14: 0 | D14: 0 | E14: 0 | F14: 0 | G14: 0 | H14: 0 | I14: 0 | J14: 0 | K14: 0 | L14: 0 | M14: 0 | N14: 0 | O14: 0
A15: Total receipts | C15: =SUM(C10:C14) -> 0 | D15: =SUM(D10:D14) -> 0 | E15: =SUM(E10:E14) -> 0 | F15: =SUM(F10:F14) -> 0 | G15: =SUM(G10:G14) -> 0 | H15: =SUM(H10:H14) -> 0 | I15: =SUM(I10:I14) -> 0 | J15: =SUM(J10:J14) -> 0 | ... O15: =SUM(O10:O14) -> 0
A17: PAYMENTS
A18: Payments to suppliers | B18: Trading | C18: 0 | D18: 0 | E18: 0 | F18: 0 | G18: 0 | H18: 0 | I18: 0 | J18: 0 | K18: 0 | L18: 0 | M18: 0 | N18: 0 | O18: 0
A19: Payroll and wages | B19: Trading | C19: 0 | D19: 0 | E19: 0 | F19: 0 | G19: 0 | H19: 0 | I19: 0 | J19: 0 | K19: 0 | L19: 0 | M19: 0 | N19: 0 | O19: 0
A20: Rent and utilities | B20: Trading | C20: 0 | D20: 0 | E20: 0 | F20: 0 | G20: 0 | H20: 0 | I20: 0 | J20: 0 | K20: 0 | L20: 0 | M20: 0 | N20: 0 | O20: 0
A21: Marketing | B21: Trading | C21: 0 | D21: 0 | E21: 0 | F21: 0 | G21: 0 | H21: 0 | I21: 0 | J21: 0 | K21: 0 | L21: 0 | M21: 0 | N21: 0 | O21: 0
A22: Professional fees | B22: Trading | C22: 0 | D22: 0 | E22: 0 | F22: 0 | G22: 0 | H22: 0 | I22: 0 | J22: 0 | K22: 0 | L22: 0 | M22: 0 | N22: 0 | O22: 0
A23: Tax payments | B23: Trading | C23: 0 | D23: 0 | E23: 0 | F23: 0 | G23: 0 | H23: 0 | I23: 0 | J23: 0 | K23: 0 | L23: 0 | M23: 0 | N23: 0 | O23: 0
A24: Loan repayments | B24: Financing | C24: 0 | D24: 0 | E24: 0 | F24: 0 | G24: 0 | H24: 0 | I24: 0 | J24: 0 | K24: 0 | L24: 0 | M24: 0 | N24: 0 | O24: 0
A25: Interest paid | B25: Financing | C25: 0 | D25: 0 | E25: 0 | F25: 0 | G25: 0 | H25: 0 | I25: 0 | J25: 0 | K25: 0 | L25: 0 | M25: 0 | N25: 0 | O25: 0
A26: Capital expenditure | B26: Investing | C26: 0 | D26: 0 | E26: 0 | F26: 0 | G26: 0 | H26: 0 | I26: 0 | J26: 0 | K26: 0 | L26: 0 | M26: 0 | N26: 0 | O26: 0
A27: Total payments | C27: =SUM(C18:C26) -> 0 | D27: =SUM(D18:D26) -> 0 | E27: =SUM(E18:E26) -> 0 | F27: =SUM(F18:F26) -> 0 | G27: =SUM(G18:G26) -> 0 | H27: =SUM(H18:H26) -> 0 | I27: =SUM(I18:I26) -> 0 | J27: =SUM(J18:J26) -> 0 | ... O27: =SUM(O18:O26) -> 0
A29: CASH POSITION
A30: Opening balance | C30: =$C$5 -> 45000 | D30: =C33 -> 45000 | E30: =D33 -> 45000 | F30: =E33 -> 45000 | G30: =F33 -> 45000 | H30: =G33 -> 45000 | I30: =H33 -> 45000 | J30: =I33 -> 45000 | K30: =J33 -> 45000 | ... O30: =N33 -> 45000
A31: Net movement | C31: =C15-C27 -> 0 | D31: =D15-D27 -> 0 | E31: =E15-E27 -> 0 | F31: =F15-F27 -> 0 | G31: =G15-G27 -> 0 | H31: =H15-H27 -> 0 | I31: =I15-I27 -> 0 | J31: =J15-J27 -> 0 | ... O31: =O15-O27 -> 0
A33: Closing balance | C33: =C30+C31 -> 45000 | D33: =D30+D31 -> 45000 | E33: =E30+E31 -> 45000 | F33: =F30+F31 -> 45000 | G33: =G30+G31 -> 45000 | H33: =H30+H31 -> 45000 | I33: =I30+I31 -> 45000 | J33: =J30+J31 -> 45000 | ... O33: =O30+O31 -> 45000
A34: Headroom over buffer | C34: =C33-$C$6 -> 25000 | D34: =D33-$C$6 -> 25000 | E34: =E33-$C$6 -> 25000 | F34: =F33-$C$6 -> 25000 | G34: =G33-$C$6 -> 25000 | H34: =H33-$C$6 -> 25000 | I34: =I33-$C$6 -> 25000 | J34: =J33-$C$6 -> 25000 | ... O34: =O33-$C$6 -> 25000
A36: Below buffer? | C36: =IF(C33<$C$6,"CHECK","") | D36: =IF(D33<$C$6,"CHECK","") | E36: =IF(E33<$C$6,"CHECK","") | F36: =IF(F33<$C$6,"CHECK","") | G36: =IF(G33<$C$6,"CHECK","") | H36: =IF(H33<$C$6,"CHECK","") | I36: =IF(I33<$C$6,"CHECK","") | J36: =IF(J33<$C$6,"CHECK","") | ... O36: =IF(O33<$C$6,"CHECK","")
A38: How to use this file
A39: Blue text | B39: You fill these in. Everything else calculates itself.
A40: Black text | B40: Formulas. Do not overwrite these.
A41: Shaded green | B41: Totals and calculated results.
A43: Note: every week header is calculated from the start date on Assumptions. Change that one date and the whole forecast shifts.

Sheet Assumptions
A1: Assumptions
A2: Change these. The forecast follows.
A4: Forecast start date | B4: 2026-01-05 | C4: Monday of week 1. Every column header on Forecast counts forward from here.
A5: Opening cash balance | B5: 45000 | C5: Bank balance on the start date, per the statement, not the ledger.
A6: Minimum cash buffer | B6: 20000 | C6: The level you do not want to drop below. Drives the headroom row and the red flags.
A8: Debtor collection assumptions
A9: Collected within 30 days | B9: 0.6 | C9: Proportion of invoices settled in the first month.
A10: Collected in 31-60 days | B10: 0.3 | C10: The next tranche.
A11: Collected in 61-90 days | B11: 0.08 | C11: Slow payers.
A12: Written off | B12: 0.02 | C12: Bad debt provision.
A13: Total | B13: =SUM(B9:B12) -> 1 | C13: Must equal 100%. If it does not, your collection profile is wrong.

Sheet Actuals
A1: Actual vs Forecast
A2: Enter what really happened. Variance calculates against the forecast.
A4: Week ending | B4: Forecast closing | C4: Actual closing | D4: Variance | E4: Variance % | F4: Comment
A5: =Forecast!C$8 -> 46027 | B5: =Forecast!C$33 -> 45000 | D5: =IF(C5="","",C5-B5) | E5: =IF(OR(C5="",B5=0),"",D5/ABS(B5))
A6: =Forecast!D$8 -> 46034 | B6: =Forecast!D$33 -> 45000 | D6: =IF(C6="","",C6-B6) | E6: =IF(OR(C6="",B6=0),"",D6/ABS(B6))
A7: =Forecast!E$8 -> 46041 | B7: =Forecast!E$33 -> 45000 | D7: =IF(C7="","",C7-B7) | E7: =IF(OR(C7="",B7=0),"",D7/ABS(B7))
A8: =Forecast!F$8 -> 46048 | B8: =Forecast!F$33 -> 45000 | D8: =IF(C8="","",C8-B8) | E8: =IF(OR(C8="",B8=0),"",D8/ABS(B8))
A9: =Forecast!G$8 -> 46055 | B9: =Forecast!G$33 -> 45000 | D9: =IF(C9="","",C9-B9) | E9: =IF(OR(C9="",B9=0),"",D9/ABS(B9))
A10: =Forecast!H$8 -> 46062 | B10: =Forecast!H$33 -> 45000 | D10: =IF(C10="","",C10-B10) | E10: =IF(OR(C10="",B10=0),"",D10/ABS(B10))
A11: =Forecast!I$8 -> 46069 | B11: =Forecast!I$33 -> 45000 | D11: =IF(C11="","",C11-B11) | E11: =IF(OR(C11="",B11=0),"",D11/ABS(B11))
A12: =Forecast!J$8 -> 46076 | B12: =Forecast!J$33 -> 45000 | D12: =IF(C12="","",C12-B12) | E12: =IF(OR(C12="",B12=0),"",D12/ABS(B12))
A13: =Forecast!K$8 -> 46083 | B13: =Forecast!K$33 -> 45000 | D13: =IF(C13="","",C13-B13) | E13: =IF(OR(C13="",B13=0),"",D13/ABS(B13))
A14: =Forecast!L$8 -> 46090 | B14: =Forecast!L$33 -> 45000 | D14: =IF(C14="","",C14-B14) | E14: =IF(OR(C14="",B14=0),"",D14/ABS(B14))
A15: =Forecast!M$8 -> 46097 | B15: =Forecast!M$33 -> 45000 | D15: =IF(C15="","",C15-B15) | E15: =IF(OR(C15="",B15=0),"",D15/ABS(B15))
A16: =Forecast!N$8 -> 46104 | B16: =Forecast!N$33 -> 45000 | D16: =IF(C16="","",C16-B16) | E16: =IF(OR(C16="",B16=0),"",D16/ABS(B16))
A17: =Forecast!O$8 -> 46111 | B17: =Forecast!O$33 -> 45000 | D17: =IF(C17="","",C17-B17) | E17: =IF(OR(C17="",B17=0),"",D17/ABS(B17))
A20: A variance you cannot explain is worth more attention than a large one you can.

Sheet Read me
A1: How this workbook works
A2: Explore Excel · exploreexcel.com
A4: What this is
A5: A rolling thirteen-week cash forecast. Thirteen weeks because it is one quarter — far enough ahead to act on a shortfall, close enough that the numbers mean something.
A7: Where to start
A8: 1. Open Assumptions and set the start date, opening balance and buffer.
A9: 2. Go to Forecast and fill in the blue cells, week by week.
A10: 3. Each Friday, enter the real closing balance on Actuals.
A12: The colour convention
A13: Blue text is an input. Black text is a formula. Green shading is a total. This is the standard used in financial models, so anyone in finance will read it without being told.
A15: What the flags mean
A16: A closing balance below zero turns red. Headroom below your buffer turns amber. The CHECK row flags any week where you drop under the buffer.
... A22: A forecast is a set of assumptions, not a prediction. The value is in noticing early that reality has diverged from what you assumed — which is why the Actuals sheet matters more than the Forecast sheet.
