Workbook

Sheet Read me
A1: How this workbook works
A4: What this is
A5: Two ways to clear the same debts. Snowball pays the smallest balance first, avalanche the highest interest rate first, and the comparison sheet shows what each one costs you in interest and how long it takes.
A7: Filling it in
A8: Put your debts on the Debts sheet — balance, rate and the minimum payment your lender requires. Then set the extra amount you can afford each month and the date of your first payment. Everything else is calculated.
A10: What the two methods do
A11: Both pay every minimum every month, then throw all spare money at one debt until it clears. Snowball picks the smallest balance, so debts disappear quickly and it feels like progress. Avalanche picks the highest rate, which always costs less in total interest. The comparison sheet puts numbers on that trade.
A13: Rolling payments
A14: When a debt clears, its minimum is not spare cash — it joins the extra payment and attacks the next debt. That is what makes either method finish years earlier than paying minimums alone, and it is why the pool column grows as you go down.
A16: Two simplifications, stated plainly
A17: Minimum payments are treated as fixed, where a real credit card recalculates its minimum as the balance falls. And in the month a debt clears, any leftover from the extra payment waits until the next month rather than moving to the next debt immediately. Both make the schedule slightly cautious, never optimistic.
A19: The check on the Debts sheet
... A26: Blue figures are yours to type over. Black figures are calculated — typing over one replaces the formula. Green shading is a heading or a total. This is the standard financial-modeling convention, so anyone in a finance or audit role will read it without being told.

Sheet Debts
A1: Debt Payoff Calculator
A2: Your debts, and what you can put against them
A4: Debt | B4: Balance | C4: Rate | D4: Minimum payment | E4: Snowball order | F4: Avalanche order
A5: Store card | B5: 900 | C5: 0.0699 | D5: 25 | E5: =COUNTIF($B$5:$B$9,"<"&B5)+COUNTIF($B$5:B5,B5) | F5: =COUNTIF($C$5:$C$9,">"&C5)+COUNTIF($C$5:C5,C5)
A6: Credit card A | B6: 6400 | C6: 0.2499 | D6: 160 | E6: =COUNTIF($B$5:$B$9,"<"&B6)+COUNTIF($B$5:B6,B6) | F6: =COUNTIF($C$5:$C$9,">"&C6)+COUNTIF($C$5:C6,C6)
A7: Credit card B | B7: 2100 | C7: 0.1899 | D7: 55 | E7: =COUNTIF($B$5:$B$9,"<"&B7)+COUNTIF($B$5:B7,B7) | F7: =COUNTIF($C$5:$C$9,">"&C7)+COUNTIF($C$5:C7,C7)
A8: Auto loan | B8: 11200 | C8: 0.0549 | D8: 310 | E8: =COUNTIF($B$5:$B$9,"<"&B8)+COUNTIF($B$5:B8,B8) | F8: =COUNTIF($C$5:$C$9,">"&C8)+COUNTIF($C$5:C8,C8)
A9: Medical bill | B9: 3500 | C9: 0 | D9: 100 | E9: =COUNTIF($B$5:$B$9,"<"&B9)+COUNTIF($B$5:B9,B9) | F9: =COUNTIF($C$5:$C$9,">"&C9)+COUNTIF($C$5:C9,C9)
A10: Total | B10: =SUM(B5:B9) | D10: =SUM(D5:D9)
A12: What you can pay
A13: Extra each month, on top of the minimums | B13: 250
A14: First payment date | B14: 46023
A15: Total going out each month | B15: =D10+B13
A17: Check
A18: Does every minimum cover its interest? | B18: =IF(SUMPRODUCT(($D$5:$D$9<=$B$5:$B$9*$C$5:$C$9/12)*($B$5:$B$9>0))=0,"Yes — every debt will clear","No — one minimum is below its monthly interest")

Sheet Snowball
A1: Snowball method
A2: Every month, every debt, to the dollar
A4: Debt | C4: =Debts!$A$5 | D4: =Debts!$A$6 | E4: =Debts!$A$7 | F4: =Debts!$A$8 | G4: =Debts!$A$9
A5: Rate | C5: =Debts!$C$5 | D5: =Debts!$C$6 | E5: =Debts!$C$7 | F5: =Debts!$C$8 | G5: =Debts!$C$9
A6: Minimum | C6: =Debts!$D$5 | D6: =Debts!$D$6 | E6: =Debts!$D$7 | F6: =Debts!$D$8 | G6: =Debts!$D$9
A7: Order paid | C7: =Debts!$E$5 | D7: =Debts!$E$6 | E7: =Debts!$E$7 | F7: =Debts!$E$8 | G7: =Debts!$E$9
A9: Month | B9: Date | C9: Interest 1 | D9: Interest 2 | E9: Interest 3 | F9: Interest 4 | G9: Interest 5 | H9: Payment 1 | I9: Payment 2 | J9: Payment 3 | K9: Payment 4 | L9: Payment 5 | M9: Balance 1 | N9: Balance 2 | O9: Balance 3 | P9: Balance 4 | Q9: Balance 5 | R9: Total paid | S9: Interest | T9: Owed after | U9: Snowball | V9: t1 | W9: t2 | X9: t3 | Y9: t4 | Z9: t5
A10: 0 | B10: =Debts!$B$14 | M10: =Debts!$B$5 | N10: =Debts!$B$6 | O10: =Debts!$B$7 | P10: =Debts!$B$8 | Q10: =Debts!$B$9 | T10: =SUM(M10:Q10)
A11: =A10+1 | B11: =EDATE(Debts!$B$14,A11) | C11: =IF(M10<=0,0,ROUND(M10*$C$5/12,2)) | D11: =IF(N10<=0,0,ROUND(N10*$D$5/12,2)) | E11: =IF(O10<=0,0,ROUND(O10*$E$5/12,2)) | F11: =IF(P10<=0,0,ROUND(P10*$F$5/12,2)) | G11: =IF(Q10<=0,0,ROUND(Q10*$G$5/12,2)) | H11: =IF(M10<=0,0,MIN(M10+C11,$C$6+V11*$U11)) | I11: =IF(N10<=0,0,MIN(N10+D11,$D$6+W11*$U11)) | J11: =IF(O10<=0,0,MIN(O10+E11,$E$6+X11*$U11)) | K11: =IF(P10<=0,0,MIN(P10+F11,$F$6+Y11*$U11)) | L11: =IF(Q10<=0,0,MIN(Q10+G11,$G$6+Z11*$U11)) | M11: =ROUND(M10+C11-H11,2) | N11: =ROUND(N10+D11-I11,2) | O11: =ROUND(O10+E11-J11,2) | P11: =ROUND(P10+F11-K11,2) | Q11: =ROUND(Q10+G11-L11,2) | R11: =SUM(H11:L11) | S11: =SUM(C11:G11) | T11: =SUM(M11:Q11) | U11: =Debts!$B$13+SUMPRODUCT(($M10:$Q10<=0)*$C$6:$G$6) | V11: =IF(AND(M10>0,SUMPRODUCT(($C$7:$G$7<$C$7)*($M10:$Q10>0))=0),1,0) | W11: =IF(AND(N10>0,SUMPRODUCT(($C$7:$G$7<$D$7)*($M10:$Q10>0))=0),1,0) | X11: =IF(AND(O10>0,SUMPRODUCT(($C$7:$G$7<$E$7)*($M10:$Q10>0))=0),1,0) | Y11: =IF(AND(P10>0,SUMPRODUCT(($C$7:$G$7<$F$7)*($M10:$Q10>0))=0),1,0) | Z11: =IF(AND(Q10>0,SUMPRODUCT(($C$7:$G$7<$G$7)*($M10:$Q10>0))=0),1,0)
A12: =A11+1 | B12: =EDATE(Debts!$B$14,A12) | C12: =IF(M11<=0,0,ROUND(M11*$C$5/12,2)) | D12: =IF(N11<=0,0,ROUND(N11*$D$5/12,2)) | E12: =IF(O11<=0,0,ROUND(O11*$E$5/12,2)) | F12: =IF(P11<=0,0,ROUND(P11*$F$5/12,2)) | G12: =IF(Q11<=0,0,ROUND(Q11*$G$5/12,2)) | H12: =IF(M11<=0,0,MIN(M11+C12,$C$6+V12*$U12)) | I12: =IF(N11<=0,0,MIN(N11+D12,$D$6+W12*$U12)) | J12: =IF(O11<=0,0,MIN(O11+E12,$E$6+X12*$U12)) | K12: =IF(P11<=0,0,MIN(P11+F12,$F$6+Y12*$U12)) | L12: =IF(Q11<=0,0,MIN(Q11+G12,$G$6+Z12*$U12)) | M12: =ROUND(M11+C12-H12,2) | N12: =ROUND(N11+D12-I12,2) | O12: =ROUND(O11+E12-J12,2) | P12: =ROUND(P11+F12-K12,2) | Q12: =ROUND(Q11+G12-L12,2) | R12: =SUM(H12:L12) | S12: =SUM(C12:G12) | T12: =SUM(M12:Q12) | U12: =Debts!$B$13+SUMPRODUCT(($M11:$Q11<=0)*$C$6:$G$6) | V12: =IF(AND(M11>0,SUMPRODUCT(($C$7:$G$7<$C$7)*($M11:$Q11>0))=0),1,0) | W12: =IF(AND(N11>0,SUMPRODUCT(($C$7:$G$7<$D$7)*($M11:$Q11>0))=0),1,0) | X12: =IF(AND(O11>0,SUMPRODUCT(($C$7:$G$7<$E$7)*($M11:$Q11>0))=0),1,0) | Y12: =IF(AND(P11>0,SUMPRODUCT(($C$7:$G$7<$F$7)*($M11:$Q11>0))=0),1,0) | Z12: =IF(AND(Q11>0,SUMPRODUCT(($C$7:$G$7<$G$7)*($M11:$Q11>0))=0),1,0)
A13: =A12+1 | B13: =EDATE(Debts!$B$14,A13) | C13: =IF(M12<=0,0,ROUND(M12*$C$5/12,2)) | D13: =IF(N12<=0,0,ROUND(N12*$D$5/12,2)) | E13: =IF(O12<=0,0,ROUND(O12*$E$5/12,2)) | F13: =IF(P12<=0,0,ROUND(P12*$F$5/12,2)) | G13: =IF(Q12<=0,0,ROUND(Q12*$G$5/12,2)) | H13: =IF(M12<=0,0,MIN(M12+C13,$C$6+V13*$U13)) | I13: =IF(N12<=0,0,MIN(N12+D13,$D$6+W13*$U13)) | J13: =IF(O12<=0,0,MIN(O12+E13,$E$6+X13*$U13)) | K13: =IF(P12<=0,0,MIN(P12+F13,$F$6+Y13*$U13)) | L13: =IF(Q12<=0,0,MIN(Q12+G13,$G$6+Z13*$U13)) | M13: =ROUND(M12+C13-H13,2) | N13: =ROUND(N12+D13-I13,2) | O13: =ROUND(O12+E13-J13,2) | P13: =ROUND(P12+F13-K13,2) | Q13: =ROUND(Q12+G13-L13,2) | R13: =SUM(H13:L13) | S13: =SUM(C13:G13) | T13: =SUM(M13:Q13) | U13: =Debts!$B$13+SUMPRODUCT(($M12:$Q12<=0)*$C$6:$G$6) | V13: =IF(AND(M12>0,SUMPRODUCT(($C$7:$G$7<$C$7)*($M12:$Q12>0))=0),1,0) | W13: =IF(AND(N12>0,SUMPRODUCT(($C$7:$G$7<$D$7)*($M12:$Q12>0))=0),1,0) | X13: =IF(AND(O12>0,SUMPRODUCT(($C$7:$G$7<$E$7)*($M12:$Q12>0))=0),1,0) | Y13: =IF(AND(P12>0,SUMPRODUCT(($C$7:$G$7<$F$7)*($M12:$Q12>0))=0),1,0) | Z13: =IF(AND(Q12>0,SUMPRODUCT(($C$7:$G$7<$G$7)*($M12:$Q12>0))=0),1,0)
A14: =A13+1 | B14: =EDATE(Debts!$B$14,A14) | C14: =IF(M13<=0,0,ROUND(M13*$C$5/12,2)) | D14: =IF(N13<=0,0,ROUND(N13*$D$5/12,2)) | E14: =IF(O13<=0,0,ROUND(O13*$E$5/12,2)) | F14: =IF(P13<=0,0,ROUND(P13*$F$5/12,2)) | G14: =IF(Q13<=0,0,ROUND(Q13*$G$5/12,2)) | H14: =IF(M13<=0,0,MIN(M13+C14,$C$6+V14*$U14)) | I14: =IF(N13<=0,0,MIN(N13+D14,$D$6+W14*$U14)) | J14: =IF(O13<=0,0,MIN(O13+E14,$E$6+X14*$U14)) | K14: =IF(P13<=0,0,MIN(P13+F14,$F$6+Y14*$U14)) | L14: =IF(Q13<=0,0,MIN(Q13+G14,$G$6+Z14*$U14)) | M14: =ROUND(M13+C14-H14,2) | N14: =ROUND(N13+D14-I14,2) | O14: =ROUND(O13+E14-J14,2) | P14: =ROUND(P13+F14-K14,2) | Q14: =ROUND(Q13+G14-L14,2) | R14: =SUM(H14:L14) | S14: =SUM(C14:G14) | T14: =SUM(M14:Q14) | U14: =Debts!$B$13+SUMPRODUCT(($M13:$Q13<=0)*$C$6:$G$6) | V14: =IF(AND(M13>0,SUMPRODUCT(($C$7:$G$7<$C$7)*($M13:$Q13>0))=0),1,0) | W14: =IF(AND(N13>0,SUMPRODUCT(($C$7:$G$7<$D$7)*($M13:$Q13>0))=0),1,0) | X14: =IF(AND(O13>0,SUMPRODUCT(($C$7:$G$7<$E$7)*($M13:$Q13>0))=0),1,0) | Y14: =IF(AND(P13>0,SUMPRODUCT(($C$7:$G$7<$F$7)*($M13:$Q13>0))=0),1,0) | Z14: =IF(AND(Q13>0,SUMPRODUCT(($C$7:$G$7<$G$7)*($M13:$Q13>0))=0),1,0)
A15: =A14+1 | B15: =EDATE(Debts!$B$14,A15) | C15: =IF(M14<=0,0,ROUND(M14*$C$5/12,2)) | D15: =IF(N14<=0,0,ROUND(N14*$D$5/12,2)) | E15: =IF(O14<=0,0,ROUND(O14*$E$5/12,2)) | F15: =IF(P14<=0,0,ROUND(P14*$F$5/12,2)) | G15: =IF(Q14<=0,0,ROUND(Q14*$G$5/12,2)) | H15: =IF(M14<=0,0,MIN(M14+C15,$C$6+V15*$U15)) | I15: =IF(N14<=0,0,MIN(N14+D15,$D$6+W15*$U15)) | J15: =IF(O14<=0,0,MIN(O14+E15,$E$6+X15*$U15)) | K15: =IF(P14<=0,0,MIN(P14+F15,$F$6+Y15*$U15)) | L15: =IF(Q14<=0,0,MIN(Q14+G15,$G$6+Z15*$U15)) | M15: =ROUND(M14+C15-H15,2) | N15: =ROUND(N14+D15-I15,2) | O15: =ROUND(O14+E15-J15,2) | P15: =ROUND(P14+F15-K15,2) | Q15: =ROUND(Q14+G15-L15,2) | R15: =SUM(H15:L15) | S15: =SUM(C15:G15) | T15: =SUM(M15:Q15) | U15: =Debts!$B$13+SUMPRODUCT(($M14:$Q14<=0)*$C$6:$G$6) | V15: =IF(AND(M14>0,SUMPRODUCT(($C$7:$G$7<$C$7)*($M14:$Q14>0))=0),1,0) | W15: =IF(AND(N14>0,SUMPRODUCT(($C$7:$G$7<$D$7)*($M14:$Q14>0))=0),1,0) | X15: =IF(AND(O14>0,SUMPRODUCT(($C$7:$G$7<$E$7)*($M14:$Q14>0))=0),1,0) | Y15: =IF(AND(P14>0,SUMPRODUCT(($C$7:$G$7<$F$7)*($M14:$Q14>0))=0),1,0) | Z15: =IF(AND(Q14>0,SUMPRODUCT(($C$7:$G$7<$G$7)*($M14:$Q14>0))=0),1,0)
A16: =A15+1 | B16: =EDATE(Debts!$B$14,A16) | C16: =IF(M15<=0,0,ROUND(M15*$C$5/12,2)) | D16: =IF(N15<=0,0,ROUND(N15*$D$5/12,2)) | E16: =IF(O15<=0,0,ROUND(O15*$E$5/12,2)) | F16: =IF(P15<=0,0,ROUND(P15*$F$5/12,2)) | G16: =IF(Q15<=0,0,ROUND(Q15*$G$5/12,2)) | H16: =IF(M15<=0,0,MIN(M15+C16,$C$6+V16*$U16)) | I16: =IF(N15<=0,0,MIN(N15+D16,$D$6+W16*$U16)) | J16: =IF(O15<=0,0,MIN(O15+E16,$E$6+X16*$U16)) | K16: =IF(P15<=0,0,MIN(P15+F16,$F$6+Y16*$U16)) | L16: =IF(Q15<=0,0,MIN(Q15+G16,$G$6+Z16*$U16)) | M16: =ROUND(M15+C16-H16,2) | N16: =ROUND(N15+D16-I16,2) | O16: =ROUND(O15+E16-J16,2) | P16: =ROUND(P15+F16-K16,2) | Q16: =ROUND(Q15+G16-L16,2) | R16: =SUM(H16:L16) | S16: =SUM(C16:G16) | T16: =SUM(M16:Q16) | U16: =Debts!$B$13+SUMPRODUCT(($M15:$Q15<=0)*$C$6:$G$6) | V16: =IF(AND(M15>0,SUMPRODUCT(($C$7:$G$7<$C$7)*($M15:$Q15>0))=0),1,0) | W16: =IF(AND(N15>0,SUMPRODUCT(($C$7:$G$7<$D$7)*($M15:$Q15>0))=0),1,0) | X16: =IF(AND(O15>0,SUMPRODUCT(($C$7:$G$7<$E$7)*($M15:$Q15>0))=0),1,0) | Y16: =IF(AND(P15>0,SUMPRODUCT(($C$7:$G$7<$F$7)*($M15:$Q15>0))=0),1,0) | Z16: =IF(AND(Q15>0,SUMPRODUCT(($C$7:$G$7<$G$7)*($M15:$Q15>0))=0),1,0)
A17: =A16+1 | B17: =EDATE(Debts!$B$14,A17) | C17: =IF(M16<=0,0,ROUND(M16*$C$5/12,2)) | D17: =IF(N16<=0,0,ROUND(N16*$D$5/12,2)) | E17: =IF(O16<=0,0,ROUND(O16*$E$5/12,2)) | F17: =IF(P16<=0,0,ROUND(P16*$F$5/12,2)) | G17: =IF(Q16<=0,0,ROUND(Q16*$G$5/12,2)) | H17: =IF(M16<=0,0,MIN(M16+C17,$C$6+V17*$U17)) | I17: =IF(N16<=0,0,MIN(N16+D17,$D$6+W17*$U17)) | J17: =IF(O16<=0,0,MIN(O16+E17,$E$6+X17*$U17)) | K17: =IF(P16<=0,0,MIN(P16+F17,$F$6+Y17*$U17)) | L17: =IF(Q16<=0,0,MIN(Q16+G17,$G$6+Z17*$U17)) | M17: =ROUND(M16+C17-H17,2) | N17: =ROUND(N16+D17-I17,2) | O17: =ROUND(O16+E17-J17,2) | P17: =ROUND(P16+F17-K17,2) | Q17: =ROUND(Q16+G17-L17,2) | R17: =SUM(H17:L17) | S17: =SUM(C17:G17) | T17: =SUM(M17:Q17) | U17: =Debts!$B$13+SUMPRODUCT(($M16:$Q16<=0)*$C$6:$G$6) | V17: =IF(AND(M16>0,SUMPRODUCT(($C$7:$G$7<$C$7)*($M16:$Q16>0))=0),1,0) | W17: =IF(AND(N16>0,SUMPRODUCT(($C$7:$G$7<$D$7)*($M16:$Q16>0))=0),1,0) | X17: =IF(AND(O16>0,SUMPRODUCT(($C$7:$G$7<$E$7)*($M16:$Q16>0))=0),1,0) | Y17: =IF(AND(P16>0,SUMPRODUCT(($C$7:$G$7<$F$7)*($M16:$Q16>0))=0),1,0) | Z17: =IF(AND(Q16>0,SUMPRODUCT(($C$7:$G$7<$G$7)*($M16:$Q16>0))=0),1,0)
A18: =A17+1 | B18: =EDATE(Debts!$B$14,A18) | C18: =IF(M17<=0,0,ROUND(M17*$C$5/12,2)) | D18: =IF(N17<=0,0,ROUND(N17*$D$5/12,2)) | E18: =IF(O17<=0,0,ROUND(O17*$E$5/12,2)) | F18: =IF(P17<=0,0,ROUND(P17*$F$5/12,2)) | G18: =IF(Q17<=0,0,ROUND(Q17*$G$5/12,2)) | H18: =IF(M17<=0,0,MIN(M17+C18,$C$6+V18*$U18)) | I18: =IF(N17<=0,0,MIN(N17+D18,$D$6+W18*$U18)) | J18: =IF(O17<=0,0,MIN(O17+E18,$E$6+X18*$U18)) | K18: =IF(P17<=0,0,MIN(P17+F18,$F$6+Y18*$U18)) | L18: =IF(Q17<=0,0,MIN(Q17+G18,$G$6+Z18*$U18)) | M18: =ROUND(M17+C18-H18,2) | N18: =ROUND(N17+D18-I18,2) | O18: =ROUND(O17+E18-J18,2) | P18: =ROUND(P17+F18-K18,2) | Q18: =ROUND(Q17+G18-L18,2) | R18: =SUM(H18:L18) | S18: =SUM(C18:G18) | T18: =SUM(M18:Q18) | U18: =Debts!$B$13+SUMPRODUCT(($M17:$Q17<=0)*$C$6:$G$6) | V18: =IF(AND(M17>0,SUMPRODUCT(($C$7:$G$7<$C$7)*($M17:$Q17>0))=0),1,0) | W18: =IF(AND(N17>0,SUMPRODUCT(($C$7:$G$7<$D$7)*($M17:$Q17>0))=0),1,0) | X18: =IF(AND(O17>0,SUMPRODUCT(($C$7:$G$7<$E$7)*($M17:$Q17>0))=0),1,0) | Y18: =IF(AND(P17>0,SUMPRODUCT(($C$7:$G$7<$F$7)*($M17:$Q17>0))=0),1,0) | Z18: =IF(AND(Q17>0,SUMPRODUCT(($C$7:$G$7<$G$7)*($M17:$Q17>0))=0),1,0)
A19: =A18+1 | B19: =EDATE(Debts!$B$14,A19) | C19: =IF(M18<=0,0,ROUND(M18*$C$5/12,2)) | D19: =IF(N18<=0,0,ROUND(N18*$D$5/12,2)) | E19: =IF(O18<=0,0,ROUND(O18*$E$5/12,2)) | F19: =IF(P18<=0,0,ROUND(P18*$F$5/12,2)) | G19: =IF(Q18<=0,0,ROUND(Q18*$G$5/12,2)) | H19: =IF(M18<=0,0,MIN(M18+C19,$C$6+V19*$U19)) | I19: =IF(N18<=0,0,MIN(N18+D19,$D$6+W19*$U19)) | J19: =IF(O18<=0,0,MIN(O18+E19,$E$6+X19*$U19)) | K19: =IF(P18<=0,0,MIN(P18+F19,$F$6+Y19*$U19)) | L19: =IF(Q18<=0,0,MIN(Q18+G19,$G$6+Z19*$U19)) | M19: =ROUND(M18+C19-H19,2) | N19: =ROUND(N18+D19-I19,2) | O19: =ROUND(O18+E19-J19,2) | P19: =ROUND(P18+F19-K19,2) | Q19: =ROUND(Q18+G19-L19,2) | R19: =SUM(H19:L19) | S19: =SUM(C19:G19) | T19: =SUM(M19:Q19) | U19: =Debts!$B$13+SUMPRODUCT(($M18:$Q18<=0)*$C$6:$G$6) | V19: =IF(AND(M18>0,SUMPRODUCT(($C$7:$G$7<$C$7)*($M18:$Q18>0))=0),1,0) | W19: =IF(AND(N18>0,SUMPRODUCT(($C$7:$G$7<$D$7)*($M18:$Q18>0))=0),1,0) | X19: =IF(AND(O18>0,SUMPRODUCT(($C$7:$G$7<$E$7)*($M18:$Q18>0))=0),1,0) | Y19: =IF(AND(P18>0,SUMPRODUCT(($C$7:$G$7<$F$7)*($M18:$Q18>0))=0),1,0) | Z19: =IF(AND(Q18>0,SUMPRODUCT(($C$7:$G$7<$G$7)*($M18:$Q18>0))=0),1,0)
A20: =A19+1 | B20: =EDATE(Debts!$B$14,A20) | C20: =IF(M19<=0,0,ROUND(M19*$C$5/12,2)) | D20: =IF(N19<=0,0,ROUND(N19*$D$5/12,2)) | E20: =IF(O19<=0,0,ROUND(O19*$E$5/12,2)) | F20: =IF(P19<=0,0,ROUND(P19*$F$5/12,2)) | G20: =IF(Q19<=0,0,ROUND(Q19*$G$5/12,2)) | H20: =IF(M19<=0,0,MIN(M19+C20,$C$6+V20*$U20)) | I20: =IF(N19<=0,0,MIN(N19+D20,$D$6+W20*$U20)) | J20: =IF(O19<=0,0,MIN(O19+E20,$E$6+X20*$U20)) | K20: =IF(P19<=0,0,MIN(P19+F20,$F$6+Y20*$U20)) | L20: =IF(Q19<=0,0,MIN(Q19+G20,$G$6+Z20*$U20)) | M20: =ROUND(M19+C20-H20,2) | N20: =ROUND(N19+D20-I20,2) | O20: =ROUND(O19+E20-J20,2) | P20: =ROUND(P19+F20-K20,2) | Q20: =ROUND(Q19+G20-L20,2) | R20: =SUM(H20:L20) | S20: =SUM(C20:G20) | T20: =SUM(M20:Q20) | U20: =Debts!$B$13+SUMPRODUCT(($M19:$Q19<=0)*$C$6:$G$6) | V20: =IF(AND(M19>0,SUMPRODUCT(($C$7:$G$7<$C$7)*($M19:$Q19>0))=0),1,0) | W20: =IF(AND(N19>0,SUMPRODUCT(($C$7:$G$7<$D$7)*($M19:$Q19>0))=0),1,0) | X20: =IF(AND(O19>0,SUMPRODUCT(($C$7:$G$7<$E$7)*($M19:$Q19>0))=0),1,0) | Y20: =IF(AND(P19>0,SUMPRODUCT(($C$7:$G$7<$F$7)*($M19:$Q19>0))=0),1,0) | Z20: =IF(AND(Q19>0,SUMPRODUCT(($C$7:$G$7<$G$7)*($M19:$Q19>0))=0),1,0)
A21: =A20+1 | B21: =EDATE(Debts!$B$14,A21) | C21: =IF(M20<=0,0,ROUND(M20*$C$5/12,2)) | D21: =IF(N20<=0,0,ROUND(N20*$D$5/12,2)) | E21: =IF(O20<=0,0,ROUND(O20*$E$5/12,2)) | F21: =IF(P20<=0,0,ROUND(P20*$F$5/12,2)) | G21: =IF(Q20<=0,0,ROUND(Q20*$G$5/12,2)) | H21: =IF(M20<=0,0,MIN(M20+C21,$C$6+V21*$U21)) | I21: =IF(N20<=0,0,MIN(N20+D21,$D$6+W21*$U21)) | J21: =IF(O20<=0,0,MIN(O20+E21,$E$6+X21*$U21)) | K21: =IF(P20<=0,0,MIN(P20+F21,$F$6+Y21*$U21)) | L21: =IF(Q20<=0,0,MIN(Q20+G21,$G$6+Z21*$U21)) | M21: =ROUND(M20+C21-H21,2) | N21: =ROUND(N20+D21-I21,2) | O21: =ROUND(O20+E21-J21,2) | P21: =ROUND(P20+F21-K21,2) | Q21: =ROUND(Q20+G21-L21,2) | R21: =SUM(H21:L21) | S21: =SUM(C21:G21) | T21: =SUM(M21:Q21) | U21: =Debts!$B$13+SUMPRODUCT(($M20:$Q20<=0)*$C$6:$G$6) | V21: =IF(AND(M20>0,SUMPRODUCT(($C$7:$G$7<$C$7)*($M20:$Q20>0))=0),1,0) | W21: =IF(AND(N20>0,SUMPRODUCT(($C$7:$G$7<$D$7)*($M20:$Q20>0))=0),1,0) | X21: =IF(AND(O20>0,SUMPRODUCT(($C$7:$G$7<$E$7)*($M20:$Q20>0))=0),1,0) | Y21: =IF(AND(P20>0,SUMPRODUCT(($C$7:$G$7<$F$7)*($M20:$Q20>0))=0),1,0) | Z21: =IF(AND(Q20>0,SUMPRODUCT(($C$7:$G$7<$G$7)*($M20:$Q20>0))=0),1,0)
A22: =A21+1 | B22: =EDATE(Debts!$B$14,A22) | C22: =IF(M21<=0,0,ROUND(M21*$C$5/12,2)) | D22: =IF(N21<=0,0,ROUND(N21*$D$5/12,2)) | E22: =IF(O21<=0,0,ROUND(O21*$E$5/12,2)) | F22: =IF(P21<=0,0,ROUND(P21*$F$5/12,2)) | G22: =IF(Q21<=0,0,ROUND(Q21*$G$5/12,2)) | H22: =IF(M21<=0,0,MIN(M21+C22,$C$6+V22*$U22)) | I22: =IF(N21<=0,0,MIN(N21+D22,$D$6+W22*$U22)) | J22: =IF(O21<=0,0,MIN(O21+E22,$E$6+X22*$U22)) | K22: =IF(P21<=0,0,MIN(P21+F22,$F$6+Y22*$U22)) | L22: =IF(Q21<=0,0,MIN(Q21+G22,$G$6+Z22*$U22)) | M22: =ROUND(M21+C22-H22,2) | N22: =ROUND(N21+D22-I22,2) | O22: =ROUND(O21+E22-J22,2) | P22: =ROUND(P21+F22-K22,2) | Q22: =ROUND(Q21+G22-L22,2) | R22: =SUM(H22:L22) | S22: =SUM(C22:G22) | T22: =SUM(M22:Q22) | U22: =Debts!$B$13+SUMPRODUCT(($M21:$Q21<=0)*$C$6:$G$6) | V22: =IF(AND(M21>0,SUMPRODUCT(($C$7:$G$7<$C$7)*($M21:$Q21>0))=0),1,0) | W22: =IF(AND(N21>0,SUMPRODUCT(($C$7:$G$7<$D$7)*($M21:$Q21>0))=0),1,0) | X22: =IF(AND(O21>0,SUMPRODUCT(($C$7:$G$7<$E$7)*($M21:$Q21>0))=0),1,0) | Y22: =IF(AND(P21>0,SUMPRODUCT(($C$7:$G$7<$F$7)*($M21:$Q21>0))=0),1,0) | Z22: =IF(AND(Q21>0,SUMPRODUCT(($C$7:$G$7<$G$7)*($M21:$Q21>0))=0),1,0)
... A130: =A129+1 | B130: =EDATE(Debts!$B$14,A130) | C130: =IF(M129<=0,0,ROUND(M129*$C$5/12,2)) | D130: =IF(N129<=0,0,ROUND(N129*$D$5/12,2)) | E130: =IF(O129<=0,0,ROUND(O129*$E$5/12,2)) | F130: =IF(P129<=0,0,ROUND(P129*$F$5/12,2)) | G130: =IF(Q129<=0,0,ROUND(Q129*$G$5/12,2)) | H130: =IF(M129<=0,0,MIN(M129+C130,$C$6+V130*$U130)) | I130: =IF(N129<=0,0,MIN(N129+D130,$D$6+W130*$U130)) | J130: =IF(O129<=0,0,MIN(O129+E130,$E$6+X130*$U130)) | K130: =IF(P129<=0,0,MIN(P129+F130,$F$6+Y130*$U130)) | L130: =IF(Q129<=0,0,MIN(Q129+G130,$G$6+Z130*$U130)) | M130: =ROUND(M129+C130-H130,2) | N130: =ROUND(N129+D130-I130,2) | O130: =ROUND(O129+E130-J130,2) | P130: =ROUND(P129+F130-K130,2) | Q130: =ROUND(Q129+G130-L130,2) | R130: =SUM(H130:L130) | S130: =SUM(C130:G130) | T130: =SUM(M130:Q130) | U130: =Debts!$B$13+SUMPRODUCT(($M129:$Q129<=0)*$C$6:$G$6) | V130: =IF(AND(M129>0,SUMPRODUCT(($C$7:$G$7<$C$7)*($M129:$Q129>0))=0),1,0) | W130: =IF(AND(N129>0,SUMPRODUCT(($C$7:$G$7<$D$7)*($M129:$Q129>0))=0),1,0) | X130: =IF(AND(O129>0,SUMPRODUCT(($C$7:$G$7<$E$7)*($M129:$Q129>0))=0),1,0) | Y130: =IF(AND(P129>0,SUMPRODUCT(($C$7:$G$7<$F$7)*($M129:$Q129>0))=0),1,0) | Z130: =IF(AND(Q129>0,SUMPRODUCT(($C$7:$G$7<$G$7)*($M129:$Q129>0))=0),1,0)

Sheet Avalanche
A1: Avalanche method
A2: Every month, every debt, to the dollar
A4: Debt | C4: =Debts!$A$5 | D4: =Debts!$A$6 | E4: =Debts!$A$7 | F4: =Debts!$A$8 | G4: =Debts!$A$9
A5: Rate | C5: =Debts!$C$5 | D5: =Debts!$C$6 | E5: =Debts!$C$7 | F5: =Debts!$C$8 | G5: =Debts!$C$9
A6: Minimum | C6: =Debts!$D$5 | D6: =Debts!$D$6 | E6: =Debts!$D$7 | F6: =Debts!$D$8 | G6: =Debts!$D$9
A7: Order paid | C7: =Debts!$F$5 | D7: =Debts!$F$6 | E7: =Debts!$F$7 | F7: =Debts!$F$8 | G7: =Debts!$F$9
A9: Month | B9: Date | C9: Interest 1 | D9: Interest 2 | E9: Interest 3 | F9: Interest 4 | G9: Interest 5 | H9: Payment 1 | I9: Payment 2 | J9: Payment 3 | K9: Payment 4 | L9: Payment 5 | M9: Balance 1 | N9: Balance 2 | O9: Balance 3 | P9: Balance 4 | Q9: Balance 5 | R9: Total paid | S9: Interest | T9: Owed after | U9: Snowball | V9: t1 | W9: t2 | X9: t3 | Y9: t4 | Z9: t5
A10: 0 | B10: =Debts!$B$14 | M10: =Debts!$B$5 | N10: =Debts!$B$6 | O10: =Debts!$B$7 | P10: =Debts!$B$8 | Q10: =Debts!$B$9 | T10: =SUM(M10:Q10)
A11: =A10+1 | B11: =EDATE(Debts!$B$14,A11) | C11: =IF(M10<=0,0,ROUND(M10*$C$5/12,2)) | D11: =IF(N10<=0,0,ROUND(N10*$D$5/12,2)) | E11: =IF(O10<=0,0,ROUND(O10*$E$5/12,2)) | F11: =IF(P10<=0,0,ROUND(P10*$F$5/12,2)) | G11: =IF(Q10<=0,0,ROUND(Q10*$G$5/12,2)) | H11: =IF(M10<=0,0,MIN(M10+C11,$C$6+V11*$U11)) | I11: =IF(N10<=0,0,MIN(N10+D11,$D$6+W11*$U11)) | J11: =IF(O10<=0,0,MIN(O10+E11,$E$6+X11*$U11)) | K11: =IF(P10<=0,0,MIN(P10+F11,$F$6+Y11*$U11)) | L11: =IF(Q10<=0,0,MIN(Q10+G11,$G$6+Z11*$U11)) | M11: =ROUND(M10+C11-H11,2) | N11: =ROUND(N10+D11-I11,2) | O11: =ROUND(O10+E11-J11,2) | P11: =ROUND(P10+F11-K11,2) | Q11: =ROUND(Q10+G11-L11,2) | R11: =SUM(H11:L11) | S11: =SUM(C11:G11) | T11: =SUM(M11:Q11) | U11: =Debts!$B$13+SUMPRODUCT(($M10:$Q10<=0)*$C$6:$G$6) | V11: =IF(AND(M10>0,SUMPRODUCT(($C$7:$G$7<$C$7)*($M10:$Q10>0))=0),1,0) | W11: =IF(AND(N10>0,SUMPRODUCT(($C$7:$G$7<$D$7)*($M10:$Q10>0))=0),1,0) | X11: =IF(AND(O10>0,SUMPRODUCT(($C$7:$G$7<$E$7)*($M10:$Q10>0))=0),1,0) | Y11: =IF(AND(P10>0,SUMPRODUCT(($C$7:$G$7<$F$7)*($M10:$Q10>0))=0),1,0) | Z11: =IF(AND(Q10>0,SUMPRODUCT(($C$7:$G$7<$G$7)*($M10:$Q10>0))=0),1,0)
A12: =A11+1 | B12: =EDATE(Debts!$B$14,A12) | C12: =IF(M11<=0,0,ROUND(M11*$C$5/12,2)) | D12: =IF(N11<=0,0,ROUND(N11*$D$5/12,2)) | E12: =IF(O11<=0,0,ROUND(O11*$E$5/12,2)) | F12: =IF(P11<=0,0,ROUND(P11*$F$5/12,2)) | G12: =IF(Q11<=0,0,ROUND(Q11*$G$5/12,2)) | H12: =IF(M11<=0,0,MIN(M11+C12,$C$6+V12*$U12)) | I12: =IF(N11<=0,0,MIN(N11+D12,$D$6+W12*$U12)) | J12: =IF(O11<=0,0,MIN(O11+E12,$E$6+X12*$U12)) | K12: =IF(P11<=0,0,MIN(P11+F12,$F$6+Y12*$U12)) | L12: =IF(Q11<=0,0,MIN(Q11+G12,$G$6+Z12*$U12)) | M12: =ROUND(M11+C12-H12,2) | N12: =ROUND(N11+D12-I12,2) | O12: =ROUND(O11+E12-J12,2) | P12: =ROUND(P11+F12-K12,2) | Q12: =ROUND(Q11+G12-L12,2) | R12: =SUM(H12:L12) | S12: =SUM(C12:G12) | T12: =SUM(M12:Q12) | U12: =Debts!$B$13+SUMPRODUCT(($M11:$Q11<=0)*$C$6:$G$6) | V12: =IF(AND(M11>0,SUMPRODUCT(($C$7:$G$7<$C$7)*($M11:$Q11>0))=0),1,0) | W12: =IF(AND(N11>0,SUMPRODUCT(($C$7:$G$7<$D$7)*($M11:$Q11>0))=0),1,0) | X12: =IF(AND(O11>0,SUMPRODUCT(($C$7:$G$7<$E$7)*($M11:$Q11>0))=0),1,0) | Y12: =IF(AND(P11>0,SUMPRODUCT(($C$7:$G$7<$F$7)*($M11:$Q11>0))=0),1,0) | Z12: =IF(AND(Q11>0,SUMPRODUCT(($C$7:$G$7<$G$7)*($M11:$Q11>0))=0),1,0)
A13: =A12+1 | B13: =EDATE(Debts!$B$14,A13) | C13: =IF(M12<=0,0,ROUND(M12*$C$5/12,2)) | D13: =IF(N12<=0,0,ROUND(N12*$D$5/12,2)) | E13: =IF(O12<=0,0,ROUND(O12*$E$5/12,2)) | F13: =IF(P12<=0,0,ROUND(P12*$F$5/12,2)) | G13: =IF(Q12<=0,0,ROUND(Q12*$G$5/12,2)) | H13: =IF(M12<=0,0,MIN(M12+C13,$C$6+V13*$U13)) | I13: =IF(N12<=0,0,MIN(N12+D13,$D$6+W13*$U13)) | J13: =IF(O12<=0,0,MIN(O12+E13,$E$6+X13*$U13)) | K13: =IF(P12<=0,0,MIN(P12+F13,$F$6+Y13*$U13)) | L13: =IF(Q12<=0,0,MIN(Q12+G13,$G$6+Z13*$U13)) | M13: =ROUND(M12+C13-H13,2) | N13: =ROUND(N12+D13-I13,2) | O13: =ROUND(O12+E13-J13,2) | P13: =ROUND(P12+F13-K13,2) | Q13: =ROUND(Q12+G13-L13,2) | R13: =SUM(H13:L13) | S13: =SUM(C13:G13) | T13: =SUM(M13:Q13) | U13: =Debts!$B$13+SUMPRODUCT(($M12:$Q12<=0)*$C$6:$G$6) | V13: =IF(AND(M12>0,SUMPRODUCT(($C$7:$G$7<$C$7)*($M12:$Q12>0))=0),1,0) | W13: =IF(AND(N12>0,SUMPRODUCT(($C$7:$G$7<$D$7)*($M12:$Q12>0))=0),1,0) | X13: =IF(AND(O12>0,SUMPRODUCT(($C$7:$G$7<$E$7)*($M12:$Q12>0))=0),1,0) | Y13: =IF(AND(P12>0,SUMPRODUCT(($C$7:$G$7<$F$7)*($M12:$Q12>0))=0),1,0) | Z13: =IF(AND(Q12>0,SUMPRODUCT(($C$7:$G$7<$G$7)*($M12:$Q12>0))=0),1,0)
A14: =A13+1 | B14: =EDATE(Debts!$B$14,A14) | C14: =IF(M13<=0,0,ROUND(M13*$C$5/12,2)) | D14: =IF(N13<=0,0,ROUND(N13*$D$5/12,2)) | E14: =IF(O13<=0,0,ROUND(O13*$E$5/12,2)) | F14: =IF(P13<=0,0,ROUND(P13*$F$5/12,2)) | G14: =IF(Q13<=0,0,ROUND(Q13*$G$5/12,2)) | H14: =IF(M13<=0,0,MIN(M13+C14,$C$6+V14*$U14)) | I14: =IF(N13<=0,0,MIN(N13+D14,$D$6+W14*$U14)) | J14: =IF(O13<=0,0,MIN(O13+E14,$E$6+X14*$U14)) | K14: =IF(P13<=0,0,MIN(P13+F14,$F$6+Y14*$U14)) | L14: =IF(Q13<=0,0,MIN(Q13+G14,$G$6+Z14*$U14)) | M14: =ROUND(M13+C14-H14,2) | N14: =ROUND(N13+D14-I14,2) | O14: =ROUND(O13+E14-J14,2) | P14: =ROUND(P13+F14-K14,2) | Q14: =ROUND(Q13+G14-L14,2) | R14: =SUM(H14:L14) | S14: =SUM(C14:G14) | T14: =SUM(M14:Q14) | U14: =Debts!$B$13+SUMPRODUCT(($M13:$Q13<=0)*$C$6:$G$6) | V14: =IF(AND(M13>0,SUMPRODUCT(($C$7:$G$7<$C$7)*($M13:$Q13>0))=0),1,0) | W14: =IF(AND(N13>0,SUMPRODUCT(($C$7:$G$7<$D$7)*($M13:$Q13>0))=0),1,0) | X14: =IF(AND(O13>0,SUMPRODUCT(($C$7:$G$7<$E$7)*($M13:$Q13>0))=0),1,0) | Y14: =IF(AND(P13>0,SUMPRODUCT(($C$7:$G$7<$F$7)*($M13:$Q13>0))=0),1,0) | Z14: =IF(AND(Q13>0,SUMPRODUCT(($C$7:$G$7<$G$7)*($M13:$Q13>0))=0),1,0)
A15: =A14+1 | B15: =EDATE(Debts!$B$14,A15) | C15: =IF(M14<=0,0,ROUND(M14*$C$5/12,2)) | D15: =IF(N14<=0,0,ROUND(N14*$D$5/12,2)) | E15: =IF(O14<=0,0,ROUND(O14*$E$5/12,2)) | F15: =IF(P14<=0,0,ROUND(P14*$F$5/12,2)) | G15: =IF(Q14<=0,0,ROUND(Q14*$G$5/12,2)) | H15: =IF(M14<=0,0,MIN(M14+C15,$C$6+V15*$U15)) | I15: =IF(N14<=0,0,MIN(N14+D15,$D$6+W15*$U15)) | J15: =IF(O14<=0,0,MIN(O14+E15,$E$6+X15*$U15)) | K15: =IF(P14<=0,0,MIN(P14+F15,$F$6+Y15*$U15)) | L15: =IF(Q14<=0,0,MIN(Q14+G15,$G$6+Z15*$U15)) | M15: =ROUND(M14+C15-H15,2) | N15: =ROUND(N14+D15-I15,2) | O15: =ROUND(O14+E15-J15,2) | P15: =ROUND(P14+F15-K15,2) | Q15: =ROUND(Q14+G15-L15,2) | R15: =SUM(H15:L15) | S15: =SUM(C15:G15) | T15: =SUM(M15:Q15) | U15: =Debts!$B$13+SUMPRODUCT(($M14:$Q14<=0)*$C$6:$G$6) | V15: =IF(AND(M14>0,SUMPRODUCT(($C$7:$G$7<$C$7)*($M14:$Q14>0))=0),1,0) | W15: =IF(AND(N14>0,SUMPRODUCT(($C$7:$G$7<$D$7)*($M14:$Q14>0))=0),1,0) | X15: =IF(AND(O14>0,SUMPRODUCT(($C$7:$G$7<$E$7)*($M14:$Q14>0))=0),1,0) | Y15: =IF(AND(P14>0,SUMPRODUCT(($C$7:$G$7<$F$7)*($M14:$Q14>0))=0),1,0) | Z15: =IF(AND(Q14>0,SUMPRODUCT(($C$7:$G$7<$G$7)*($M14:$Q14>0))=0),1,0)
A16: =A15+1 | B16: =EDATE(Debts!$B$14,A16) | C16: =IF(M15<=0,0,ROUND(M15*$C$5/12,2)) | D16: =IF(N15<=0,0,ROUND(N15*$D$5/12,2)) | E16: =IF(O15<=0,0,ROUND(O15*$E$5/12,2)) | F16: =IF(P15<=0,0,ROUND(P15*$F$5/12,2)) | G16: =IF(Q15<=0,0,ROUND(Q15*$G$5/12,2)) | H16: =IF(M15<=0,0,MIN(M15+C16,$C$6+V16*$U16)) | I16: =IF(N15<=0,0,MIN(N15+D16,$D$6+W16*$U16)) | J16: =IF(O15<=0,0,MIN(O15+E16,$E$6+X16*$U16)) | K16: =IF(P15<=0,0,MIN(P15+F16,$F$6+Y16*$U16)) | L16: =IF(Q15<=0,0,MIN(Q15+G16,$G$6+Z16*$U16)) | M16: =ROUND(M15+C16-H16,2) | N16: =ROUND(N15+D16-I16,2) | O16: =ROUND(O15+E16-J16,2) | P16: =ROUND(P15+F16-K16,2) | Q16: =ROUND(Q15+G16-L16,2) | R16: =SUM(H16:L16) | S16: =SUM(C16:G16) | T16: =SUM(M16:Q16) | U16: =Debts!$B$13+SUMPRODUCT(($M15:$Q15<=0)*$C$6:$G$6) | V16: =IF(AND(M15>0,SUMPRODUCT(($C$7:$G$7<$C$7)*($M15:$Q15>0))=0),1,0) | W16: =IF(AND(N15>0,SUMPRODUCT(($C$7:$G$7<$D$7)*($M15:$Q15>0))=0),1,0) | X16: =IF(AND(O15>0,SUMPRODUCT(($C$7:$G$7<$E$7)*($M15:$Q15>0))=0),1,0) | Y16: =IF(AND(P15>0,SUMPRODUCT(($C$7:$G$7<$F$7)*($M15:$Q15>0))=0),1,0) | Z16: =IF(AND(Q15>0,SUMPRODUCT(($C$7:$G$7<$G$7)*($M15:$Q15>0))=0),1,0)
A17: =A16+1 | B17: =EDATE(Debts!$B$14,A17) | C17: =IF(M16<=0,0,ROUND(M16*$C$5/12,2)) | D17: =IF(N16<=0,0,ROUND(N16*$D$5/12,2)) | E17: =IF(O16<=0,0,ROUND(O16*$E$5/12,2)) | F17: =IF(P16<=0,0,ROUND(P16*$F$5/12,2)) | G17: =IF(Q16<=0,0,ROUND(Q16*$G$5/12,2)) | H17: =IF(M16<=0,0,MIN(M16+C17,$C$6+V17*$U17)) | I17: =IF(N16<=0,0,MIN(N16+D17,$D$6+W17*$U17)) | J17: =IF(O16<=0,0,MIN(O16+E17,$E$6+X17*$U17)) | K17: =IF(P16<=0,0,MIN(P16+F17,$F$6+Y17*$U17)) | L17: =IF(Q16<=0,0,MIN(Q16+G17,$G$6+Z17*$U17)) | M17: =ROUND(M16+C17-H17,2) | N17: =ROUND(N16+D17-I17,2) | O17: =ROUND(O16+E17-J17,2) | P17: =ROUND(P16+F17-K17,2) | Q17: =ROUND(Q16+G17-L17,2) | R17: =SUM(H17:L17) | S17: =SUM(C17:G17) | T17: =SUM(M17:Q17) | U17: =Debts!$B$13+SUMPRODUCT(($M16:$Q16<=0)*$C$6:$G$6) | V17: =IF(AND(M16>0,SUMPRODUCT(($C$7:$G$7<$C$7)*($M16:$Q16>0))=0),1,0) | W17: =IF(AND(N16>0,SUMPRODUCT(($C$7:$G$7<$D$7)*($M16:$Q16>0))=0),1,0) | X17: =IF(AND(O16>0,SUMPRODUCT(($C$7:$G$7<$E$7)*($M16:$Q16>0))=0),1,0) | Y17: =IF(AND(P16>0,SUMPRODUCT(($C$7:$G$7<$F$7)*($M16:$Q16>0))=0),1,0) | Z17: =IF(AND(Q16>0,SUMPRODUCT(($C$7:$G$7<$G$7)*($M16:$Q16>0))=0),1,0)
A18: =A17+1 | B18: =EDATE(Debts!$B$14,A18) | C18: =IF(M17<=0,0,ROUND(M17*$C$5/12,2)) | D18: =IF(N17<=0,0,ROUND(N17*$D$5/12,2)) | E18: =IF(O17<=0,0,ROUND(O17*$E$5/12,2)) | F18: =IF(P17<=0,0,ROUND(P17*$F$5/12,2)) | G18: =IF(Q17<=0,0,ROUND(Q17*$G$5/12,2)) | H18: =IF(M17<=0,0,MIN(M17+C18,$C$6+V18*$U18)) | I18: =IF(N17<=0,0,MIN(N17+D18,$D$6+W18*$U18)) | J18: =IF(O17<=0,0,MIN(O17+E18,$E$6+X18*$U18)) | K18: =IF(P17<=0,0,MIN(P17+F18,$F$6+Y18*$U18)) | L18: =IF(Q17<=0,0,MIN(Q17+G18,$G$6+Z18*$U18)) | M18: =ROUND(M17+C18-H18,2) | N18: =ROUND(N17+D18-I18,2) | O18: =ROUND(O17+E18-J18,2) | P18: =ROUND(P17+F18-K18,2) | Q18: =ROUND(Q17+G18-L18,2) | R18: =SUM(H18:L18) | S18: =SUM(C18:G18) | T18: =SUM(M18:Q18) | U18: =Debts!$B$13+SUMPRODUCT(($M17:$Q17<=0)*$C$6:$G$6) | V18: =IF(AND(M17>0,SUMPRODUCT(($C$7:$G$7<$C$7)*($M17:$Q17>0))=0),1,0) | W18: =IF(AND(N17>0,SUMPRODUCT(($C$7:$G$7<$D$7)*($M17:$Q17>0))=0),1,0) | X18: =IF(AND(O17>0,SUMPRODUCT(($C$7:$G$7<$E$7)*($M17:$Q17>0))=0),1,0) | Y18: =IF(AND(P17>0,SUMPRODUCT(($C$7:$G$7<$F$7)*($M17:$Q17>0))=0),1,0) | Z18: =IF(AND(Q17>0,SUMPRODUCT(($C$7:$G$7<$G$7)*($M17:$Q17>0))=0),1,0)
A19: =A18+1 | B19: =EDATE(Debts!$B$14,A19) | C19: =IF(M18<=0,0,ROUND(M18*$C$5/12,2)) | D19: =IF(N18<=0,0,ROUND(N18*$D$5/12,2)) | E19: =IF(O18<=0,0,ROUND(O18*$E$5/12,2)) | F19: =IF(P18<=0,0,ROUND(P18*$F$5/12,2)) | G19: =IF(Q18<=0,0,ROUND(Q18*$G$5/12,2)) | H19: =IF(M18<=0,0,MIN(M18+C19,$C$6+V19*$U19)) | I19: =IF(N18<=0,0,MIN(N18+D19,$D$6+W19*$U19)) | J19: =IF(O18<=0,0,MIN(O18+E19,$E$6+X19*$U19)) | K19: =IF(P18<=0,0,MIN(P18+F19,$F$6+Y19*$U19)) | L19: =IF(Q18<=0,0,MIN(Q18+G19,$G$6+Z19*$U19)) | M19: =ROUND(M18+C19-H19,2) | N19: =ROUND(N18+D19-I19,2) | O19: =ROUND(O18+E19-J19,2) | P19: =ROUND(P18+F19-K19,2) | Q19: =ROUND(Q18+G19-L19,2) | R19: =SUM(H19:L19) | S19: =SUM(C19:G19) | T19: =SUM(M19:Q19) | U19: =Debts!$B$13+SUMPRODUCT(($M18:$Q18<=0)*$C$6:$G$6) | V19: =IF(AND(M18>0,SUMPRODUCT(($C$7:$G$7<$C$7)*($M18:$Q18>0))=0),1,0) | W19: =IF(AND(N18>0,SUMPRODUCT(($C$7:$G$7<$D$7)*($M18:$Q18>0))=0),1,0) | X19: =IF(AND(O18>0,SUMPRODUCT(($C$7:$G$7<$E$7)*($M18:$Q18>0))=0),1,0) | Y19: =IF(AND(P18>0,SUMPRODUCT(($C$7:$G$7<$F$7)*($M18:$Q18>0))=0),1,0) | Z19: =IF(AND(Q18>0,SUMPRODUCT(($C$7:$G$7<$G$7)*($M18:$Q18>0))=0),1,0)
A20: =A19+1 | B20: =EDATE(Debts!$B$14,A20) | C20: =IF(M19<=0,0,ROUND(M19*$C$5/12,2)) | D20: =IF(N19<=0,0,ROUND(N19*$D$5/12,2)) | E20: =IF(O19<=0,0,ROUND(O19*$E$5/12,2)) | F20: =IF(P19<=0,0,ROUND(P19*$F$5/12,2)) | G20: =IF(Q19<=0,0,ROUND(Q19*$G$5/12,2)) | H20: =IF(M19<=0,0,MIN(M19+C20,$C$6+V20*$U20)) | I20: =IF(N19<=0,0,MIN(N19+D20,$D$6+W20*$U20)) | J20: =IF(O19<=0,0,MIN(O19+E20,$E$6+X20*$U20)) | K20: =IF(P19<=0,0,MIN(P19+F20,$F$6+Y20*$U20)) | L20: =IF(Q19<=0,0,MIN(Q19+G20,$G$6+Z20*$U20)) | M20: =ROUND(M19+C20-H20,2) | N20: =ROUND(N19+D20-I20,2) | O20: =ROUND(O19+E20-J20,2) | P20: =ROUND(P19+F20-K20,2) | Q20: =ROUND(Q19+G20-L20,2) | R20: =SUM(H20:L20) | S20: =SUM(C20:G20) | T20: =SUM(M20:Q20) | U20: =Debts!$B$13+SUMPRODUCT(($M19:$Q19<=0)*$C$6:$G$6) | V20: =IF(AND(M19>0,SUMPRODUCT(($C$7:$G$7<$C$7)*($M19:$Q19>0))=0),1,0) | W20: =IF(AND(N19>0,SUMPRODUCT(($C$7:$G$7<$D$7)*($M19:$Q19>0))=0),1,0) | X20: =IF(AND(O19>0,SUMPRODUCT(($C$7:$G$7<$E$7)*($M19:$Q19>0))=0),1,0) | Y20: =IF(AND(P19>0,SUMPRODUCT(($C$7:$G$7<$F$7)*($M19:$Q19>0))=0),1,0) | Z20: =IF(AND(Q19>0,SUMPRODUCT(($C$7:$G$7<$G$7)*($M19:$Q19>0))=0),1,0)
A21: =A20+1 | B21: =EDATE(Debts!$B$14,A21) | C21: =IF(M20<=0,0,ROUND(M20*$C$5/12,2)) | D21: =IF(N20<=0,0,ROUND(N20*$D$5/12,2)) | E21: =IF(O20<=0,0,ROUND(O20*$E$5/12,2)) | F21: =IF(P20<=0,0,ROUND(P20*$F$5/12,2)) | G21: =IF(Q20<=0,0,ROUND(Q20*$G$5/12,2)) | H21: =IF(M20<=0,0,MIN(M20+C21,$C$6+V21*$U21)) | I21: =IF(N20<=0,0,MIN(N20+D21,$D$6+W21*$U21)) | J21: =IF(O20<=0,0,MIN(O20+E21,$E$6+X21*$U21)) | K21: =IF(P20<=0,0,MIN(P20+F21,$F$6+Y21*$U21)) | L21: =IF(Q20<=0,0,MIN(Q20+G21,$G$6+Z21*$U21)) | M21: =ROUND(M20+C21-H21,2) | N21: =ROUND(N20+D21-I21,2) | O21: =ROUND(O20+E21-J21,2) | P21: =ROUND(P20+F21-K21,2) | Q21: =ROUND(Q20+G21-L21,2) | R21: =SUM(H21:L21) | S21: =SUM(C21:G21) | T21: =SUM(M21:Q21) | U21: =Debts!$B$13+SUMPRODUCT(($M20:$Q20<=0)*$C$6:$G$6) | V21: =IF(AND(M20>0,SUMPRODUCT(($C$7:$G$7<$C$7)*($M20:$Q20>0))=0),1,0) | W21: =IF(AND(N20>0,SUMPRODUCT(($C$7:$G$7<$D$7)*($M20:$Q20>0))=0),1,0) | X21: =IF(AND(O20>0,SUMPRODUCT(($C$7:$G$7<$E$7)*($M20:$Q20>0))=0),1,0) | Y21: =IF(AND(P20>0,SUMPRODUCT(($C$7:$G$7<$F$7)*($M20:$Q20>0))=0),1,0) | Z21: =IF(AND(Q20>0,SUMPRODUCT(($C$7:$G$7<$G$7)*($M20:$Q20>0))=0),1,0)
A22: =A21+1 | B22: =EDATE(Debts!$B$14,A22) | C22: =IF(M21<=0,0,ROUND(M21*$C$5/12,2)) | D22: =IF(N21<=0,0,ROUND(N21*$D$5/12,2)) | E22: =IF(O21<=0,0,ROUND(O21*$E$5/12,2)) | F22: =IF(P21<=0,0,ROUND(P21*$F$5/12,2)) | G22: =IF(Q21<=0,0,ROUND(Q21*$G$5/12,2)) | H22: =IF(M21<=0,0,MIN(M21+C22,$C$6+V22*$U22)) | I22: =IF(N21<=0,0,MIN(N21+D22,$D$6+W22*$U22)) | J22: =IF(O21<=0,0,MIN(O21+E22,$E$6+X22*$U22)) | K22: =IF(P21<=0,0,MIN(P21+F22,$F$6+Y22*$U22)) | L22: =IF(Q21<=0,0,MIN(Q21+G22,$G$6+Z22*$U22)) | M22: =ROUND(M21+C22-H22,2) | N22: =ROUND(N21+D22-I22,2) | O22: =ROUND(O21+E22-J22,2) | P22: =ROUND(P21+F22-K22,2) | Q22: =ROUND(Q21+G22-L22,2) | R22: =SUM(H22:L22) | S22: =SUM(C22:G22) | T22: =SUM(M22:Q22) | U22: =Debts!$B$13+SUMPRODUCT(($M21:$Q21<=0)*$C$6:$G$6) | V22: =IF(AND(M21>0,SUMPRODUCT(($C$7:$G$7<$C$7)*($M21:$Q21>0))=0),1,0) | W22: =IF(AND(N21>0,SUMPRODUCT(($C$7:$G$7<$D$7)*($M21:$Q21>0))=0),1,0) | X22: =IF(AND(O21>0,SUMPRODUCT(($C$7:$G$7<$E$7)*($M21:$Q21>0))=0),1,0) | Y22: =IF(AND(P21>0,SUMPRODUCT(($C$7:$G$7<$F$7)*($M21:$Q21>0))=0),1,0) | Z22: =IF(AND(Q21>0,SUMPRODUCT(($C$7:$G$7<$G$7)*($M21:$Q21>0))=0),1,0)
... A130: =A129+1 | B130: =EDATE(Debts!$B$14,A130) | C130: =IF(M129<=0,0,ROUND(M129*$C$5/12,2)) | D130: =IF(N129<=0,0,ROUND(N129*$D$5/12,2)) | E130: =IF(O129<=0,0,ROUND(O129*$E$5/12,2)) | F130: =IF(P129<=0,0,ROUND(P129*$F$5/12,2)) | G130: =IF(Q129<=0,0,ROUND(Q129*$G$5/12,2)) | H130: =IF(M129<=0,0,MIN(M129+C130,$C$6+V130*$U130)) | I130: =IF(N129<=0,0,MIN(N129+D130,$D$6+W130*$U130)) | J130: =IF(O129<=0,0,MIN(O129+E130,$E$6+X130*$U130)) | K130: =IF(P129<=0,0,MIN(P129+F130,$F$6+Y130*$U130)) | L130: =IF(Q129<=0,0,MIN(Q129+G130,$G$6+Z130*$U130)) | M130: =ROUND(M129+C130-H130,2) | N130: =ROUND(N129+D130-I130,2) | O130: =ROUND(O129+E130-J130,2) | P130: =ROUND(P129+F130-K130,2) | Q130: =ROUND(Q129+G130-L130,2) | R130: =SUM(H130:L130) | S130: =SUM(C130:G130) | T130: =SUM(M130:Q130) | U130: =Debts!$B$13+SUMPRODUCT(($M129:$Q129<=0)*$C$6:$G$6) | V130: =IF(AND(M129>0,SUMPRODUCT(($C$7:$G$7<$C$7)*($M129:$Q129>0))=0),1,0) | W130: =IF(AND(N129>0,SUMPRODUCT(($C$7:$G$7<$D$7)*($M129:$Q129>0))=0),1,0) | X130: =IF(AND(O129>0,SUMPRODUCT(($C$7:$G$7<$E$7)*($M129:$Q129>0))=0),1,0) | Y130: =IF(AND(P129>0,SUMPRODUCT(($C$7:$G$7<$F$7)*($M129:$Q129>0))=0),1,0) | Z130: =IF(AND(Q129>0,SUMPRODUCT(($C$7:$G$7<$G$7)*($M129:$Q129>0))=0),1,0)

Sheet Comparison
A1: Snowball or Avalanche
A2: The same debts, two orders, two totals
A4: Method | B4: Months to clear | C4: Debt free | D4: Interest paid | E4: Total paid
A5: Snowball — smallest balance first | B5: =COUNTIF(Snowball!$R$11:$R$130,">0") | C5: =INDEX(Snowball!$B$11:$B$130,COUNTIF(Snowball!$R$11:$R$130,">0")) | D5: =SUM(Snowball!$S$11:$S$130) | E5: =SUM(Snowball!$R$11:$R$130)
A6: Avalanche — highest rate first | B6: =COUNTIF(Avalanche!$R$11:$R$130,">0") | C6: =INDEX(Avalanche!$B$11:$B$130,COUNTIF(Avalanche!$R$11:$R$130,">0")) | D6: =SUM(Avalanche!$S$11:$S$130) | E6: =SUM(Avalanche!$R$11:$R$130)
A7: Avalanche saves | B7: =B5-B6 | C7: months / dollars | D7: =D5-D6 | E7: =E5-E6
A9: Which to choose
A10: Avalanche always wins on arithmetic — it is the definition of paying the most expensive money back first. Snowball wins on the thing arithmetic does not measure, which is whether you keep going. If the gap in interest is small, take the one you will actually finish.
