Workbook

Sheet Read me
A2: Invoice template
A3: How to use this template
B5: What this does
B6: Produces one printable invoice that totals itself and calculates sales tax, plus a log of what you have sent.
B8: Using it
B9: 1. Fill in your own details once on the Settings sheet. They flow onto every invoice.
B10: 2. On the Invoice sheet, fill the cream cells: client block, invoice number and date.
B11: 3. Enter the line items. Amount, subtotal, sales tax and total all calculate.
B12: 4. Print to PDF. The page is already set to fit one sheet of US Letter portrait.
B14: Sales tax
B15: The rate comes from the Settings sheet. The 8.25% shown is a placeholder only — sales tax varies by state and often by city, so set the rate that applies where you are. Set it to 0 if you do not collect sales tax; the line then shows zero rather than disappearing, which is the correct thing to show a client.
B17: Keeping a record
B18: Add a row to the Invoice log as you send each one. The outstanding figure at the top totals everything still marked Unpaid.
B20: Blue text on a cream background marks a cell you fill in. Black text is calculated — typing over one replaces the formula. Green shading is a heading or a total. This is the standard financial-modeling convention.

Sheet Settings
A1: Your details
A2: Entered once, used on every invoice
A4: Field | B4: Value
A5: Business name | B5: Your Business LLC
A6: Address line 1 | B6: 1200 Market Street
A7: Address line 2 | B7: Suite 400
A8: City, State ZIP | B8: Austin, TX 78701
A9: Email | B9: hello@yourbusiness.com
A10: Phone | B10: (512) 555-0100
A11: EIN or Tax ID | B11: 00-0000000
A12: Sales tax rate | B12: 0.0825
A13: Bank account name | B13: Your Business LLC
A14: Routing number | B14: 000000000
A15: Account number | B15: 00000000
A16: Payment terms (days) | B16: 30

Sheet Invoice
A1: =Settings!B5 | D1: INVOICE
A2: =Settings!B6 | C2: Invoice number | D2: INV-0001
A3: =Settings!B7 | C3: Invoice date | D3: 46030
A4: =Settings!B8 | C4: Due date | D4: =D3+Settings!$B$16
A5: =Settings!B9
A7: Bill to
A8: Client name
A9: Client address
A10: City, State ZIP
A11: Country
A13: Description | B13: Quantity | C13: Unit price | D13: Amount
A14: Consultancy, October | B14: 12 | C14: 65 | D14: =IF(B14="","",B14*C14)
A15: Spreadsheet build and handover | B15: 1 | C15: 900 | D15: =IF(B15="","",B15*C15)
A16: Training session, half day | B16: 2 | C16: 350 | D16: =IF(B16="","",B16*C16)
D17: =IF(B17="","",B17*C17)
D18: =IF(B18="","",B18*C18)
D19: =IF(B19="","",B19*C19)
D20: =IF(B20="","",B20*C20)
D21: =IF(B21="","",B21*C21)
D22: =IF(B22="","",B22*C22)
D23: =IF(B23="","",B23*C23)
D24: =IF(B24="","",B24*C24)
D25: =IF(B25="","",B25*C25)
D26: =IF(B26="","",B26*C26)
C27: Subtotal | D27: =SUM(D14:D26)
C28: Sales tax | D28: =ROUND(D27*Settings!$B$12,2)
C29: Total due | D29: =D27+D28
A31: Payment details
A32: Account name | B32: =Settings!B13
A33: Routing number | B33: =Settings!B14
A34: Account number | B34: =Settings!B15
A36: ="Payment due within "&Settings!$B$16&" days of the invoice date."

Sheet Invoice log
A1: Invoice log
A2: One row per invoice sent
A4: OUTSTANDING
A5: =SUMIFS(E8:E107,F8:F107,"Unpaid")
A7: Invoice number | B7: Client | C7: Issued | D7: Due | E7: Amount | F7: Status
A8: INV-0001 | B8: Northaero Inc | C8: 46030 | D8: 46060 | E8: 2020 | F8: Unpaid
A9: INV-0002 | B9: Southend Components | C9: 46033 | D9: 46063 | E9: 780 | F9: Paid
