Workbook

Sheet Read me
A1: How this workbook works
A2: Explore Excel · exploreexcel.com
A4: What this is
A5: A twelve-month personal budget. Income and spending by category for every month of the year, with the surplus or deficit each month and the running balance that follows from it.
A7: Filling it in
A8: Type over the blue figures on the Planner sheet. Every line runs across twelve months, so a cost that changes with the season — utilities, gifts in December — can be entered month by month rather than averaged into something that is wrong all year.
A10: The two rows that matter
A11: Surplus or deficit is that month on its own: income less everything you spent. Running balance carries it forward, so it answers the question the monthly figure cannot — whether a good January is still covering you by June.
A13: The Summary sheet
A14: Pick any month in the blue cell and the whole sheet re-reads for that month. It finds the column with MATCH and pulls the figures with INDEX, which is why it works in every version of Excel rather than only the recent ones.
A16: Savings is an expense here
A17: Money moved to an emergency fund or a retirement account sits in the expense block deliberately. Treating it as something left over at the end is how it stops happening; treating it as a bill you pay yourself is how it does not.
... A23: Blue figures are yours to type over. Black figures are calculated — typing over one replaces the formula. Green shading is a heading or a total. This is the standard financial-modeling convention, so anyone in a finance or audit role will read it without being told.

Sheet Planner
A1: Personal Budget Planner
A2: Explore Excel · exploreexcel.com · Twelve months, income against spending
A4: Line | B4: Category | C4: Jan | D4: Feb | E4: Mar | F4: Apr | G4: May | H4: Jun | I4: Jul | J4: Aug | K4: Sep | L4: Oct | M4: Nov | N4: Dec | O4: Year
A5: INCOME
A6: Take-home pay | B6: Income | C6: 4200 | D6: 4200 | E6: 4200 | F6: 4200 | G6: 4200 | H6: 4200 | I6: 4200 | J6: 4200 | K6: 4200 | L6: 4200 | M6: 4200 | N6: 4200 | O6: =SUM(C6:N6)
A7: Second income | B7: Income | C7: 1150 | D7: 1150 | E7: 1150 | F7: 1150 | G7: 1150 | H7: 1150 | I7: 1150 | J7: 1150 | K7: 1150 | L7: 1150 | M7: 1150 | N7: 1150 | O7: =SUM(C7:N7)
A8: Other income | B8: Income | C8: 0 | D8: 0 | E8: 0 | F8: 0 | G8: 0 | H8: 300 | I8: 0 | J8: 0 | K8: 0 | L8: 0 | M8: 0 | N8: 250 | O8: =SUM(C8:N8)
A9: Total income | C9: =SUM(C6:C8) | D9: =SUM(D6:D8) | E9: =SUM(E6:E8) | F9: =SUM(F6:F8) | G9: =SUM(G6:G8) | H9: =SUM(H6:H8) | I9: =SUM(I6:I8) | J9: =SUM(J6:J8) | ... N9: =SUM(N6:N8) | O9: =SUM(C9:N9)
A11: EXPENSES
A12: Rent or mortgage | B12: Housing | C12: 1450 | D12: 1450 | E12: 1450 | F12: 1450 | G12: 1450 | H12: 1450 | I12: 1450 | J12: 1450 | K12: 1450 | L12: 1450 | M12: 1450 | N12: 1450 | O12: =SUM(C12:N12)
A13: Utilities | B13: Housing | C13: 265 | D13: 250 | E13: 180 | F13: 180 | G13: 180 | H13: 180 | I13: 230 | J13: 235 | K13: 180 | L13: 180 | M13: 180 | N13: 240 | O13: =SUM(C13:N13)
A14: Home insurance | B14: Housing | C14: 95 | D14: 95 | E14: 95 | F14: 95 | G14: 95 | H14: 95 | I14: 95 | J14: 95 | K14: 95 | L14: 95 | M14: 95 | N14: 95 | O14: =SUM(C14:N14)
A15: Repairs and maintenance | B15: Housing | C15: 60 | D15: 60 | E15: 60 | F15: 400 | G15: 60 | H15: 60 | I15: 60 | J15: 60 | K15: 220 | L15: 60 | M15: 60 | N15: 60 | O15: =SUM(C15:N15)
A16: Groceries | B16: Food | C16: 620 | D16: 620 | E16: 620 | F16: 620 | G16: 620 | H16: 620 | I16: 620 | J16: 620 | K16: 620 | L16: 620 | M16: 700 | N16: 760 | O16: =SUM(C16:N16)
A17: Eating out | B17: Food | C17: 180 | D17: 180 | E17: 180 | F17: 180 | G17: 180 | H17: 180 | I17: 180 | J17: 180 | K17: 180 | L17: 180 | M17: 180 | N17: 260 | O17: =SUM(C17:N17)
A18: Car payment | B18: Transport | C18: 340 | D18: 340 | E18: 340 | F18: 340 | G18: 340 | H18: 340 | I18: 340 | J18: 340 | K18: 340 | L18: 340 | M18: 340 | N18: 340 | O18: =SUM(C18:N18)
A19: Fuel | B19: Transport | C19: 145 | D19: 145 | E19: 145 | F19: 145 | G19: 145 | H19: 145 | I19: 190 | J19: 185 | K19: 145 | L19: 145 | M19: 145 | N19: 145 | O19: =SUM(C19:N19)
A20: Auto insurance | B20: Transport | C20: 120 | D20: 120 | E20: 120 | F20: 120 | G20: 120 | H20: 120 | I20: 120 | J20: 120 | K20: 120 | L20: 120 | M20: 120 | N20: 120 | O20: =SUM(C20:N20)
A21: Credit card payment | B21: Debt | C21: 250 | D21: 250 | E21: 250 | F21: 250 | G21: 250 | H21: 250 | I21: 250 | J21: 250 | K21: 250 | L21: 250 | M21: 250 | N21: 250 | O21: =SUM(C21:N21)
A22: Student loan | B22: Debt | C22: 310 | D22: 310 | E22: 310 | F22: 310 | G22: 310 | H22: 310 | I22: 310 | J22: 310 | K22: 310 | L22: 310 | M22: 310 | N22: 310 | O22: =SUM(C22:N22)
A23: Emergency fund | B23: Savings | C23: 300 | D23: 300 | E23: 300 | F23: 300 | G23: 300 | H23: 300 | I23: 300 | J23: 300 | K23: 300 | L23: 300 | M23: 300 | N23: 300 | O23: =SUM(C23:N23)
... A28: Gifts and giving | B28: Discretionary | C28: 75 | D28: 75 | E28: 75 | F28: 75 | G28: 75 | H28: 75 | I28: 75 | J28: 75 | K28: 75 | L28: 75 | M28: 75 | N28: 480 | O28: =SUM(C28:N28)
A29: Total spending | C29: =SUM(C12:C28) | D29: =SUM(D12:D28) | E29: =SUM(E12:E28) | F29: =SUM(F12:F28) | G29: =SUM(G12:G28) | H29: =SUM(H12:H28) | I29: =SUM(I12:I28) | J29: =SUM(J12:J28) | ... N29: =SUM(N12:N28) | O29: =SUM(C29:N29)
A31: Surplus / (deficit) | C31: =C9-C29 | D31: =D9-D29 | E31: =E9-E29 | F31: =F9-F29 | G31: =G9-G29 | H31: =H9-H29 | I31: =I9-I29 | J31: =J9-J29 | ... N31: =N9-N29 | O31: =SUM(C31:N31)
A32: Running balance | C32: =C31 | D32: =C32+D31 | E32: =D32+E31 | F32: =E32+F31 | G32: =F32+G31 | H32: =G32+H31 | I32: =H32+I31 | J32: =I32+J31 | K32: =J32+K31 | ... N32: =M32+N31 | O32: =N32

Sheet Summary
A1: Summary
A2: Explore Excel · exploreexcel.com · One month in focus, and the year behind it
A4: Month in focus | B4: Mar
A6: Category | B6: This month | C6: Year total | D6: Share of income
A7: Housing | B7: =SUMPRODUCT((Planner!$B$12:$B$28=$A7)*INDEX(Planner!$C$12:$N$28,0,MATCH($B$4,Planner!$C$4:$N$4,0))) | C7: =SUMIF(Planner!$B$12:$B$28,$A7,Planner!$O$12:$O$28) | D7: =IFERROR(C7/Planner!$O$9,0)
A8: Food | B8: =SUMPRODUCT((Planner!$B$12:$B$28=$A8)*INDEX(Planner!$C$12:$N$28,0,MATCH($B$4,Planner!$C$4:$N$4,0))) | C8: =SUMIF(Planner!$B$12:$B$28,$A8,Planner!$O$12:$O$28) | D8: =IFERROR(C8/Planner!$O$9,0)
A9: Transport | B9: =SUMPRODUCT((Planner!$B$12:$B$28=$A9)*INDEX(Planner!$C$12:$N$28,0,MATCH($B$4,Planner!$C$4:$N$4,0))) | C9: =SUMIF(Planner!$B$12:$B$28,$A9,Planner!$O$12:$O$28) | D9: =IFERROR(C9/Planner!$O$9,0)
A10: Debt | B10: =SUMPRODUCT((Planner!$B$12:$B$28=$A10)*INDEX(Planner!$C$12:$N$28,0,MATCH($B$4,Planner!$C$4:$N$4,0))) | C10: =SUMIF(Planner!$B$12:$B$28,$A10,Planner!$O$12:$O$28) | D10: =IFERROR(C10/Planner!$O$9,0)
A11: Savings | B11: =SUMPRODUCT((Planner!$B$12:$B$28=$A11)*INDEX(Planner!$C$12:$N$28,0,MATCH($B$4,Planner!$C$4:$N$4,0))) | C11: =SUMIF(Planner!$B$12:$B$28,$A11,Planner!$O$12:$O$28) | D11: =IFERROR(C11/Planner!$O$9,0)
A12: Discretionary | B12: =SUMPRODUCT((Planner!$B$12:$B$28=$A12)*INDEX(Planner!$C$12:$N$28,0,MATCH($B$4,Planner!$C$4:$N$4,0))) | C12: =SUMIF(Planner!$B$12:$B$28,$A12,Planner!$O$12:$O$28) | D12: =IFERROR(C12/Planner!$O$9,0)
A13: Total spending | B13: =SUM(B7:B12) | C13: =SUM(C7:C12) | D13: =SUM(D7:D12)
A15: Where the month lands
A16: Income | B16: =INDEX(Planner!$C$9:$N$9,MATCH($B$4,Planner!$C$4:$N$4,0)) | C16: =Planner!$O$9
A17: Spending | B17: =INDEX(Planner!$C$29:$N$29,MATCH($B$4,Planner!$C$4:$N$4,0)) | C17: =Planner!$O$29
A18: Surplus / (deficit) | B18: =B16-B17 | C18: =C16-C17
A19: Savings rate | B19: =IFERROR(B11/B16,0) | C19: =IFERROR(C11/C16,0)
A21: Check
A22: Categories against the planner | B22: =IF(ROUND(C13-Planner!$O$29,2)=0,"Agrees","Out by "&TEXT(C13-Planner!$O$29,"#,##0"))
