Workbook

Sheet Read me
A1: How this workbook works
A2: Explore Excel · exploreexcel.com
A4: What this is
A5: A purchase order you can send to a vendor, and a running log of every order raised. The log ages each order against the delivery date you promised yourself, the same way the invoice register ages what customers owe you — one is money coming in, this is what you have committed to spend.
A7: Setting it up once
A8: Fill in the Settings sheet: your details, your sales tax rate, and how long a vendor normally takes. Those flow onto every order, and the expected delivery date calculates itself from the lead time so you are not guessing.
A10: Raising an order
A11: On the Purchase Order sheet fill the blue cells — PO number, date, the vendor block, and the line items. Quantity times unit price gives the line total, tax comes from Settings, and the page is already set to print on one sheet.
A13: The log is the point
A14: A purchase order on its own is paperwork. The log is what stops an order being forgotten: add a row as you send each one, put the value received against it as goods arrive, and the Days late and Delivery status columns take care of themselves.
A16: How ageing works here
A17: Ageing runs from the expected delivery date against today, so it changes every time you open the file. An order is On schedule until that date passes, then moves through the 30, 60 and 90 day buckets. Once the received value matches the order value it drops out entirely and reads Received.
... A26: Blue figures are yours to type over. Black figures are calculated — typing over one replaces the formula. Green shading is a heading or a total. This is the standard financial-modeling convention, so anyone in a finance or audit role will read it without being told.

Sheet Settings
A1: Settings
A2: Explore Excel · exploreexcel.com · Entered once, used on every order
A4: Field | B4: Value
A5: Business name | B5: Your Business Ltd
A6: Address line 1 | B6: 12 Example Street
A7: Address line 2 | B7: Columbus
A8: State and ZIP | B8: OH 43004
A9: Email | B9: purchasing@yourbusiness.com
A10: Phone | B10: (614) 555 0100
A11: Sales tax rate | B11: 0.0875
A12: Standard lead time (days) | B12: 21
A13: Payment terms (days) | B13: 30

Sheet Purchase Order
A1: Purchase Order
A2: Explore Excel · exploreexcel.com · One order, ready to send
A4: =Settings!B5 | C4: PO number | D4: PO-1046
A5: =Settings!B6 | C5: Date raised | D5: 46238
A6: =Settings!B7 | C6: Expected delivery | D6: =IF(D5="","",D5+Settings!$B$12)
A7: =Settings!B8 | C7: Payment terms | D7: =Settings!$B$13&" days from invoice"
A8: =Settings!B9
A9: =Settings!B10
A10: Vendor | C10: Deliver to
A11: Vendor name | C11: Site or warehouse
A12: Address | C12: Address
A13: Description | B13: Quantity | C13: Unit price | D13: Line total
A14: Aluminum bracket, 3 mm | B14: 250 | C14: 4.85 | D14: =IF(B14="","",ROUND(B14*C14,2))
A15: Hex bolt M8 x 40, zinc | B15: 1000 | C15: 0.42 | D15: =IF(B15="","",ROUND(B15*C15,2))
A16: Thread lock compound, 50 ml | B16: 24 | C16: 11.75 | D16: =IF(B16="","",ROUND(B16*C16,2))
A17: Freight and handling | B17: 1 | C17: 85 | D17: =IF(B17="","",ROUND(B17*C17,2))
D18: =IF(B18="","",ROUND(B18*C18,2))
D19: =IF(B19="","",ROUND(B19*C19,2))
D20: =IF(B20="","",ROUND(B20*C20,2))
D21: =IF(B21="","",ROUND(B21*C21,2))
D22: =IF(B22="","",ROUND(B22*C22,2))
D23: =IF(B23="","",ROUND(B23*C23,2))
D24: =IF(B24="","",ROUND(B24*C24,2))
D25: =IF(B25="","",ROUND(B25*C25,2))
D26: =IF(B26="","",ROUND(B26*C26,2))
C27: Subtotal | D27: =SUM(D14:D26)
C28: Sales tax | D28: =ROUND(D27*Settings!$B$11,2)
C29: Order total | D29: =D27+D28
A31: Terms
A32: Deliver to the address above on or before the expected delivery date. Quote the PO number on the packing slip and the invoice; an invoice without it may be returned. Partial deliveries are accepted and should be noted on the packing slip.
A34: Authorized by | C34: Date

Sheet PO Log
A1: Purchase Order Log
A2: Explore Excel · exploreexcel.com · Ageing runs from the expected delivery date
A4: Today's date | C4: =TODAY() | D4: Ageing is measured against this. It updates every time you open the file.
A6: PO no. | B6: Vendor | C6: Raised | D6: Expected | E6: Order value | F6: Received | G6: Outstanding | H6: Days late | I6: Delivery status | K6: Action
A7: PO-1041 | B7: Northaero Supplies | C7: 46210 | D7: 46231 | E7: 2174.46 | F7: 2174.46 | G7: =IF(E7="","",E7-N(F7)) | H7: =IF(OR(D7="",G7=""),"",IF(G7<=0,0,MAX(0,$C$4-D7))) | I7: =IF(H7="","",IF(G7<=0,"Received",IF(H7=0,"On schedule",IF(H7<=30,"1-30 days",IF(H7<=60,"31-60 days",IF(H7<=90,"61-90 days","90+ days")))))) | K7: =IF(A7="","",IF(G7<=0,"Complete",IF(H7>0,"Chase vendor",IF(D7-$C$4<=7,"Due soon","Open"))))
A8: PO-1042 | B8: Southend Components | C8: 46215 | D8: 46236 | E8: 3480 | F8: 0 | G8: =IF(E8="","",E8-N(F8)) | H8: =IF(OR(D8="",G8=""),"",IF(G8<=0,0,MAX(0,$C$4-D8))) | I8: =IF(H8="","",IF(G8<=0,"Received",IF(H8=0,"On schedule",IF(H8<=30,"1-30 days",IF(H8<=60,"31-60 days",IF(H8<=90,"61-90 days","90+ days")))))) | K8: =IF(A8="","",IF(G8<=0,"Complete",IF(H8>0,"Chase vendor",IF(D8-$C$4<=7,"Due soon","Open"))))
A9: PO-1043 | B9: Westmoor Fabrication | C9: 46224 | D9: 46252 | E9: 1290.75 | F9: 0 | G9: =IF(E9="","",E9-N(F9)) | H9: =IF(OR(D9="",G9=""),"",IF(G9<=0,0,MAX(0,$C$4-D9))) | I9: =IF(H9="","",IF(G9<=0,"Received",IF(H9=0,"On schedule",IF(H9<=30,"1-30 days",IF(H9<=60,"31-60 days",IF(H9<=90,"61-90 days","90+ days")))))) | K9: =IF(A9="","",IF(G9<=0,"Complete",IF(H9>0,"Chase vendor",IF(D9-$C$4<=7,"Due soon","Open"))))
A10: PO-1044 | B10: Northaero Supplies | C10: 46180 | D10: 46201 | E10: 940 | F10: 400 | G10: =IF(E10="","",E10-N(F10)) | H10: =IF(OR(D10="",G10=""),"",IF(G10<=0,0,MAX(0,$C$4-D10))) | I10: =IF(H10="","",IF(G10<=0,"Received",IF(H10=0,"On schedule",IF(H10<=30,"1-30 days",IF(H10<=60,"31-60 days",IF(H10<=90,"61-90 days","90+ days")))))) | K10: =IF(A10="","",IF(G10<=0,"Complete",IF(H10>0,"Chase vendor",IF(D10-$C$4<=7,"Due soon","Open"))))
A11: PO-1045 | B11: Delta Castings | C11: 46232 | D11: 46266 | E11: 5600 | F11: 0 | G11: =IF(E11="","",E11-N(F11)) | H11: =IF(OR(D11="",G11=""),"",IF(G11<=0,0,MAX(0,$C$4-D11))) | I11: =IF(H11="","",IF(G11<=0,"Received",IF(H11=0,"On schedule",IF(H11<=30,"1-30 days",IF(H11<=60,"31-60 days",IF(H11<=90,"61-90 days","90+ days")))))) | K11: =IF(A11="","",IF(G11<=0,"Complete",IF(H11>0,"Chase vendor",IF(D11-$C$4<=7,"Due soon","Open"))))
G12: =IF(E12="","",E12-N(F12)) | H12: =IF(OR(D12="",G12=""),"",IF(G12<=0,0,MAX(0,$C$4-D12))) | I12: =IF(H12="","",IF(G12<=0,"Received",IF(H12=0,"On schedule",IF(H12<=30,"1-30 days",IF(H12<=60,"31-60 days",IF(H12<=90,"61-90 days","90+ days")))))) | K12: =IF(A12="","",IF(G12<=0,"Complete",IF(H12>0,"Chase vendor",IF(D12-$C$4<=7,"Due soon","Open"))))
G13: =IF(E13="","",E13-N(F13)) | H13: =IF(OR(D13="",G13=""),"",IF(G13<=0,0,MAX(0,$C$4-D13))) | I13: =IF(H13="","",IF(G13<=0,"Received",IF(H13=0,"On schedule",IF(H13<=30,"1-30 days",IF(H13<=60,"31-60 days",IF(H13<=90,"61-90 days","90+ days")))))) | K13: =IF(A13="","",IF(G13<=0,"Complete",IF(H13>0,"Chase vendor",IF(D13-$C$4<=7,"Due soon","Open"))))
G14: =IF(E14="","",E14-N(F14)) | H14: =IF(OR(D14="",G14=""),"",IF(G14<=0,0,MAX(0,$C$4-D14))) | I14: =IF(H14="","",IF(G14<=0,"Received",IF(H14=0,"On schedule",IF(H14<=30,"1-30 days",IF(H14<=60,"31-60 days",IF(H14<=90,"61-90 days","90+ days")))))) | K14: =IF(A14="","",IF(G14<=0,"Complete",IF(H14>0,"Chase vendor",IF(D14-$C$4<=7,"Due soon","Open"))))
G15: =IF(E15="","",E15-N(F15)) | H15: =IF(OR(D15="",G15=""),"",IF(G15<=0,0,MAX(0,$C$4-D15))) | I15: =IF(H15="","",IF(G15<=0,"Received",IF(H15=0,"On schedule",IF(H15<=30,"1-30 days",IF(H15<=60,"31-60 days",IF(H15<=90,"61-90 days","90+ days")))))) | K15: =IF(A15="","",IF(G15<=0,"Complete",IF(H15>0,"Chase vendor",IF(D15-$C$4<=7,"Due soon","Open"))))
G16: =IF(E16="","",E16-N(F16)) | H16: =IF(OR(D16="",G16=""),"",IF(G16<=0,0,MAX(0,$C$4-D16))) | I16: =IF(H16="","",IF(G16<=0,"Received",IF(H16=0,"On schedule",IF(H16<=30,"1-30 days",IF(H16<=60,"31-60 days",IF(H16<=90,"61-90 days","90+ days")))))) | K16: =IF(A16="","",IF(G16<=0,"Complete",IF(H16>0,"Chase vendor",IF(D16-$C$4<=7,"Due soon","Open"))))
G17: =IF(E17="","",E17-N(F17)) | H17: =IF(OR(D17="",G17=""),"",IF(G17<=0,0,MAX(0,$C$4-D17))) | I17: =IF(H17="","",IF(G17<=0,"Received",IF(H17=0,"On schedule",IF(H17<=30,"1-30 days",IF(H17<=60,"31-60 days",IF(H17<=90,"61-90 days","90+ days")))))) | K17: =IF(A17="","",IF(G17<=0,"Complete",IF(H17>0,"Chase vendor",IF(D17-$C$4<=7,"Due soon","Open"))))
G18: =IF(E18="","",E18-N(F18)) | H18: =IF(OR(D18="",G18=""),"",IF(G18<=0,0,MAX(0,$C$4-D18))) | I18: =IF(H18="","",IF(G18<=0,"Received",IF(H18=0,"On schedule",IF(H18<=30,"1-30 days",IF(H18<=60,"31-60 days",IF(H18<=90,"61-90 days","90+ days")))))) | K18: =IF(A18="","",IF(G18<=0,"Complete",IF(H18>0,"Chase vendor",IF(D18-$C$4<=7,"Due soon","Open"))))
G19: =IF(E19="","",E19-N(F19)) | H19: =IF(OR(D19="",G19=""),"",IF(G19<=0,0,MAX(0,$C$4-D19))) | I19: =IF(H19="","",IF(G19<=0,"Received",IF(H19=0,"On schedule",IF(H19<=30,"1-30 days",IF(H19<=60,"31-60 days",IF(H19<=90,"61-90 days","90+ days")))))) | K19: =IF(A19="","",IF(G19<=0,"Complete",IF(H19>0,"Chase vendor",IF(D19-$C$4<=7,"Due soon","Open"))))
G20: =IF(E20="","",E20-N(F20)) | H20: =IF(OR(D20="",G20=""),"",IF(G20<=0,0,MAX(0,$C$4-D20))) | I20: =IF(H20="","",IF(G20<=0,"Received",IF(H20=0,"On schedule",IF(H20<=30,"1-30 days",IF(H20<=60,"31-60 days",IF(H20<=90,"61-90 days","90+ days")))))) | K20: =IF(A20="","",IF(G20<=0,"Complete",IF(H20>0,"Chase vendor",IF(D20-$C$4<=7,"Due soon","Open"))))
G21: =IF(E21="","",E21-N(F21)) | H21: =IF(OR(D21="",G21=""),"",IF(G21<=0,0,MAX(0,$C$4-D21))) | I21: =IF(H21="","",IF(G21<=0,"Received",IF(H21=0,"On schedule",IF(H21<=30,"1-30 days",IF(H21<=60,"31-60 days",IF(H21<=90,"61-90 days","90+ days")))))) | K21: =IF(A21="","",IF(G21<=0,"Complete",IF(H21>0,"Chase vendor",IF(D21-$C$4<=7,"Due soon","Open"))))
G22: =IF(E22="","",E22-N(F22)) | H22: =IF(OR(D22="",G22=""),"",IF(G22<=0,0,MAX(0,$C$4-D22))) | I22: =IF(H22="","",IF(G22<=0,"Received",IF(H22=0,"On schedule",IF(H22<=30,"1-30 days",IF(H22<=60,"31-60 days",IF(H22<=90,"61-90 days","90+ days")))))) | K22: =IF(A22="","",IF(G22<=0,"Complete",IF(H22>0,"Chase vendor",IF(D22-$C$4<=7,"Due soon","Open"))))
G23: =IF(E23="","",E23-N(F23)) | H23: =IF(OR(D23="",G23=""),"",IF(G23<=0,0,MAX(0,$C$4-D23))) | I23: =IF(H23="","",IF(G23<=0,"Received",IF(H23=0,"On schedule",IF(H23<=30,"1-30 days",IF(H23<=60,"31-60 days",IF(H23<=90,"61-90 days","90+ days")))))) | K23: =IF(A23="","",IF(G23<=0,"Complete",IF(H23>0,"Chase vendor",IF(D23-$C$4<=7,"Due soon","Open"))))
... G206: =IF(E206="","",E206-N(F206)) | H206: =IF(OR(D206="",G206=""),"",IF(G206<=0,0,MAX(0,$C$4-D206))) | I206: =IF(H206="","",IF(G206<=0,"Received",IF(H206=0,"On schedule",IF(H206<=30,"1-30 days",IF(H206<=60,"31-60 days",IF(H206<=90,"61-90 days","90+ days")))))) | K206: =IF(A206="","",IF(G206<=0,"Complete",IF(H206>0,"Chase vendor",IF(D206-$C$4<=7,"Due soon","Open"))))

Sheet Summary
A1: Commitments Summary
A2: Explore Excel · exploreexcel.com · All figures pull from the PO Log
A4: Ageing profile
A5: Bucket | B5: Orders | C5: Outstanding | D5: % of total
A6: On schedule | B6: =COUNTIFS('PO Log'!$I$7:$I$206,A6) | C6: =SUMIFS('PO Log'!$G$7:$G$206,'PO Log'!$I$7:$I$206,A6) | D6: =IFERROR(C6/$C$11,0)
A7: 1-30 days | B7: =COUNTIFS('PO Log'!$I$7:$I$206,A7) | C7: =SUMIFS('PO Log'!$G$7:$G$206,'PO Log'!$I$7:$I$206,A7) | D7: =IFERROR(C7/$C$11,0)
A8: 31-60 days | B8: =COUNTIFS('PO Log'!$I$7:$I$206,A8) | C8: =SUMIFS('PO Log'!$G$7:$G$206,'PO Log'!$I$7:$I$206,A8) | D8: =IFERROR(C8/$C$11,0)
A9: 61-90 days | B9: =COUNTIFS('PO Log'!$I$7:$I$206,A9) | C9: =SUMIFS('PO Log'!$G$7:$G$206,'PO Log'!$I$7:$I$206,A9) | D9: =IFERROR(C9/$C$11,0)
A10: 90+ days | B10: =COUNTIFS('PO Log'!$I$7:$I$206,A10) | C10: =SUMIFS('PO Log'!$G$7:$G$206,'PO Log'!$I$7:$I$206,A10) | D10: =IFERROR(C10/$C$11,0)
A11: Total outstanding | B11: =SUM(B6:B10) | C11: =SUM(C6:C10) | D11: =IFERROR(C11/$C$11,0)
A13: Key figures
A14: Orders raised | C14: =COUNTA('PO Log'!$A$7:$A$206) | E14: Every row with a PO number.
A15: Fully received | C15: =COUNTIFS('PO Log'!$K$7:$K$206,"Complete") | E15: Received value matches the order value.
A16: Needing a chase today | C16: =COUNTIFS('PO Log'!$K$7:$K$206,"Chase vendor") | E16: Past the expected date and not fully received.
A17: Total committed | C17: =SUM('PO Log'!$E$7:$E$206) | E17: Value of every order raised.
A18: Value still to arrive | C18: =SUM('PO Log'!$G$7:$G$206) | E18: Ordered but not yet received.
A19: Overdue value | C19: =SUMIFS('PO Log'!$G$7:$G$206,'PO Log'!$H$7:$H$206,">0") | E19: The part of that which is already late.
A21: Check
A22: Buckets against the log | C22: =IF(ROUND(C11-C18,2)=0,"Agrees","Out by "&TEXT(C11-C18,"#,##0.00"))
